[
  {
    "name": "CA$H CRU$H",
    "price": 1.0,
    "totalTickets": 2463984,
    "remainingTickets": 150303,
    "gameNumber": "668",
    "tiers": [
      {
        "prize": 1000,
        "remaining": 5,
        "total": 5
      }
    ]
  },
  {
    "name": "$",
    "price": 1.0,
    "totalTickets": 27731538,
    "remainingTickets": 166389,
    "gameNumber": "690",
    "tiers": [
      {
        "prize": 2000,
        "remaining": 1,
        "total": 1
      }
    ]
  },
  {
    "name": "CA$H IN",
    "price": 1.0,
    "totalTickets": 2125769,
    "remainingTickets": 518687,
    "gameNumber": "694",
    "tiers": [
      {
        "prize": 1000,
        "remaining": 6,
        "total": 6
      }
    ]
  },
  {
    "name": "CASH BLAST",
    "price": 2.0,
    "totalTickets": 20715897,
    "remainingTickets": 62147,
    "gameNumber": "624",
    "tiers": [
      {
        "prize": 10000,
        "remaining": 2,
        "total": 2
      }
    ]
  },
  {
    "name": "MULTIPLIER MANIA",
    "price": 2.0,
    "totalTickets": 3955524,
    "remainingTickets": 87021,
    "gameNumber": "628",
    "tiers": [
      {
        "prize": 1000,
        "remaining": 1,
        "total": 1
      }
    ]
  },
  {
    "name": "TIC TAC MULTIPLIER",
    "price": 2.0,
    "totalTickets": 51206923,
    "remainingTickets": 102413,
    "gameNumber": "638",
    "tiers": [
      {
        "prize": 10000,
        "remaining": 1,
        "total": 1
      }
    ]
  },
  {
    "name": "COUNT `EM UP",
    "price": 2.0,
    "totalTickets": 1836329,
    "remainingTickets": 297485,
    "gameNumber": "662",
    "tiers": [
      {
        "prize": 15000,
        "remaining": 2,
        "total": 2
      }
    ]
  },
  {
    "name": "WIN WIN WIN",
    "price": 2.0,
    "totalTickets": 1090389,
    "remainingTickets": 185366,
    "gameNumber": "669",
    "tiers": [
      {
        "prize": 1000,
        "remaining": 4,
        "total": 4
      }
    ]
  },
  {
    "name": "PINBALL PAYOUT",
    "price": 2.0,
    "totalTickets": 1948045,
    "remainingTickets": 144155,
    "gameNumber": "673",
    "tiers": [
      {
        "prize": 1000,
        "remaining": 1,
        "total": 1
      }
    ]
  },
  {
    "name": "BASEBALL",
    "price": 2.0,
    "totalTickets": 945505,
    "remainingTickets": 451005,
    "gameNumber": "675",
    "tiers": [
      {
        "prize": 10000,
        "remaining": 2,
        "total": 2
      }
    ]
  },
  {
    "name": "ACE IN THE HOLE",
    "price": 2.0,
    "totalTickets": 1941030,
    "remainingTickets": 188279,
    "gameNumber": "680",
    "tiers": [
      {
        "prize": 1000,
        "remaining": 2,
        "total": 2
      }
    ]
  },
  {
    "name": "10X THE WIN",
    "price": 2.0,
    "totalTickets": 2305777,
    "remainingTickets": 645617,
    "gameNumber": "687",
    "tiers": [
      {
        "prize": 20000,
        "remaining": 3,
        "total": 3
      }
    ]
  },
  {
    "name": "LUCKY DOG",
    "price": 2.0,
    "totalTickets": 2585747,
    "remainingTickets": 137044,
    "gameNumber": "691",
    "tiers": [
      {
        "prize": 1000,
        "remaining": 1,
        "total": 1
      }
    ]
  },
  {
    "name": "ALL THE MONEY",
    "price": 2.0,
    "totalTickets": 1173059,
    "remainingTickets": 769526,
    "gameNumber": "705",
    "tiers": [
      {
        "prize": 10000,
        "remaining": 5,
        "total": 5
      }
    ]
  },
  {
    "name": "ELECTRIC 8`S",
    "price": 2.0,
    "totalTickets": 1314415,
    "remainingTickets": 591486,
    "gameNumber": "708",
    "tiers": [
      {
        "prize": 8888,
        "remaining": 2,
        "total": 2
      }
    ]
  },
  {
    "name": "BONUS CARD BINGO",
    "price": 3.0,
    "totalTickets": 1954171,
    "remainingTickets": 240363,
    "gameNumber": "641",
    "tiers": [
      {
        "prize": 1500,
        "remaining": 3,
        "total": 3
      }
    ]
  },
  {
    "name": "MAINE CROSSWORD",
    "price": 3.0,
    "totalTickets": 8787504,
    "remainingTickets": 1177525,
    "gameNumber": "647",
    "tiers": [
      {
        "prize": 30000,
        "remaining": 7,
        "total": 7
      }
    ]
  },
  {
    "name": "DRAGONFLY DOLLARS",
    "price": 3.0,
    "totalTickets": 1438141,
    "remainingTickets": 414184,
    "gameNumber": "648",
    "tiers": [
      {
        "prize": 30000,
        "remaining": 1,
        "total": 1
      }
    ]
  },
  {
    "name": "CASH LINE BINGO",
    "price": 3.0,
    "totalTickets": 1987751,
    "remainingTickets": 341893,
    "gameNumber": "695",
    "tiers": [
      {
        "prize": 30000,
        "remaining": 1,
        "total": 1
      }
    ]
  },
  {
    "name": "SKEE-BALL",
    "price": 3.0,
    "totalTickets": 2425316,
    "remainingTickets": 303164,
    "gameNumber": "696",
    "tiers": [
      {
        "prize": 30000,
        "remaining": 1,
        "total": 1
      }
    ]
  },
  {
    "name": "LEAP FOR LOOT",
    "price": 3.0,
    "totalTickets": 1740087,
    "remainingTickets": 549867,
    "gameNumber": "699",
    "tiers": [
      {
        "prize": 30000,
        "remaining": 1,
        "total": 1
      }
    ]
  },
  {
    "name": "HIGH ROLLER",
    "price": 5.0,
    "totalTickets": 0,
    "remainingTickets": 0,
    "gameNumber": "617",
    "tiers": [
      {
        "prize": 1000,
        "remaining": 2,
        "total": 2
      }
    ]
  },
  {
    "name": "$5 MAINE LOTTERY 50",
    "price": 5.0,
    "totalTickets": 7600769,
    "remainingTickets": 45604,
    "gameNumber": "636",
    "tiers": [
      {
        "prize": 1000,
        "remaining": 2,
        "total": 2
      }
    ]
  },
  {
    "name": "$100,000 BONUS PAYOUT",
    "price": 5.0,
    "totalTickets": 3703956,
    "remainingTickets": 51855,
    "gameNumber": "649",
    "tiers": [
      {
        "prize": 1000,
        "remaining": 4,
        "total": 4
      }
    ]
  },
  {
    "name": "MONEY TO GO!",
    "price": 5.0,
    "totalTickets": 1604733,
    "remainingTickets": 83446,
    "gameNumber": "654",
    "tiers": [
      {
        "prize": 10000,
        "remaining": 1,
        "total": 1
      }
    ]
  },
  {
    "name": "POWER SPOT",
    "price": 5.0,
    "totalTickets": 1658532,
    "remainingTickets": 502535,
    "gameNumber": "656",
    "tiers": [
      {
        "prize": 100000,
        "remaining": 1,
        "total": 1
      }
    ]
  },
  {
    "name": "9`S IN A LINE",
    "price": 5.0,
    "totalTickets": 4340341,
    "remainingTickets": 39063,
    "gameNumber": "663",
    "tiers": [
      {
        "prize": 1000,
        "remaining": 2,
        "total": 2
      }
    ]
  },
  {
    "name": "$100,000 WINNING 7",
    "price": 5.0,
    "totalTickets": 1860523,
    "remainingTickets": 87444,
    "gameNumber": "664",
    "tiers": [
      {
        "prize": 1000,
        "remaining": 2,
        "total": 2
      }
    ]
  },
  {
    "name": "SHOW ME THE BENJAMINS",
    "price": 5.0,
    "totalTickets": 3488639,
    "remainingTickets": 45352,
    "gameNumber": "670",
    "tiers": [
      {
        "prize": 10000,
        "remaining": 2,
        "total": 2
      }
    ]
  },
  {
    "name": "$100,000 JACKPOT",
    "price": 5.0,
    "totalTickets": 1091202,
    "remainingTickets": 232426,
    "gameNumber": "671",
    "tiers": [
      {
        "prize": 10000,
        "remaining": 2,
        "total": 2
      }
    ]
  },
  {
    "name": "CROSSWORD BONUS",
    "price": 5.0,
    "totalTickets": 2546730,
    "remainingTickets": 142616,
    "gameNumber": "676",
    "tiers": [
      {
        "prize": 1000,
        "remaining": 5,
        "total": 5
      }
    ]
  },
  {
    "name": "$100,000 STACKS OF CASH",
    "price": 5.0,
    "totalTickets": 1108541,
    "remainingTickets": 138567,
    "gameNumber": "681",
    "tiers": [
      {
        "prize": 1000,
        "remaining": 12,
        "total": 12
      }
    ]
  },
  {
    "name": "LADY LUCK",
    "price": 5.0,
    "totalTickets": 4806730,
    "remainingTickets": 153815,
    "gameNumber": "683",
    "tiers": [
      {
        "prize": 100000,
        "remaining": 1,
        "total": 1
      }
    ]
  },
  {
    "name": "WINNING STREAK",
    "price": 5.0,
    "totalTickets": 1486655,
    "remainingTickets": 205158,
    "gameNumber": "684",
    "tiers": [
      {
        "prize": 10000,
        "remaining": 1,
        "total": 1
      }
    ]
  },
  {
    "name": "20X THE WIN",
    "price": 5.0,
    "totalTickets": 2287251,
    "remainingTickets": 487184,
    "gameNumber": "685",
    "tiers": [
      {
        "prize": 100000,
        "remaining": 2,
        "total": 2
      }
    ]
  },
  {
    "name": "DEUCE$ WILD POKER",
    "price": 5.0,
    "totalTickets": 8065230,
    "remainingTickets": 40326,
    "gameNumber": "689",
    "tiers": [
      {
        "prize": 5000,
        "remaining": 1,
        "total": 1
      }
    ]
  },
  {
    "name": "MONEY VAULT MULTIPLIER",
    "price": 5.0,
    "totalTickets": 1698274,
    "remainingTickets": 854231,
    "gameNumber": "692",
    "tiers": [
      {
        "prize": 100000,
        "remaining": 2,
        "total": 2
      }
    ]
  },
  {
    "name": "PATRIOTS",
    "price": 5.0,
    "totalTickets": 1232429,
    "remainingTickets": 373425,
    "gameNumber": "697",
    "tiers": [
      {
        "prize": 100000,
        "remaining": 1,
        "total": 1
      }
    ]
  },
  {
    "name": "HOLIDAY $500S",
    "price": 5.0,
    "totalTickets": 13201923,
    "remainingTickets": 52807,
    "gameNumber": "702",
    "tiers": [
      {
        "prize": 500,
        "remaining": 36,
        "total": 36
      }
    ]
  },
  {
    "name": "SILVER 7S",
    "price": 5.0,
    "totalTickets": 1987677,
    "remainingTickets": 337905,
    "gameNumber": "704",
    "tiers": [
      {
        "prize": 77777,
        "remaining": 1,
        "total": 1
      }
    ]
  },
  {
    "name": "DOUBLE YOUR DOLLARS",
    "price": 5.0,
    "totalTickets": 2205928,
    "remainingTickets": 240446,
    "gameNumber": "706",
    "tiers": [
      {
        "prize": 100000,
        "remaining": 1,
        "total": 1
      }
    ]
  },
  {
    "name": "$60,000 CASHWORD",
    "price": 5.0,
    "totalTickets": 3230688,
    "remainingTickets": 429681,
    "gameNumber": "707",
    "tiers": [
      {
        "prize": 60000,
        "remaining": 1,
        "total": 1
      }
    ]
  },
  {
    "name": "CA$H BLA$T",
    "price": 5.0,
    "totalTickets": 1345347,
    "remainingTickets": 449345,
    "gameNumber": "709",
    "tiers": [
      {
        "prize": 100000,
        "remaining": 1,
        "total": 1
      }
    ]
  },
  {
    "name": "$500 CA$H!",
    "price": 5.0,
    "totalTickets": 0,
    "remainingTickets": 0,
    "gameNumber": "710",
    "tiers": [
      {
        "prize": 500,
        "remaining": 62,
        "total": 62
      }
    ]
  },
  {
    "name": "HI OR LO",
    "price": 5.0,
    "totalTickets": 1288338,
    "remainingTickets": 693125,
    "gameNumber": "717",
    "tiers": [
      {
        "prize": 100000,
        "remaining": 2,
        "total": 2
      }
    ]
  },
  {
    "name": "RED HOT RICHES",
    "price": 5.0,
    "totalTickets": 1356219,
    "remainingTickets": 869336,
    "gameNumber": "723",
    "tiers": [
      {
        "prize": 100000,
        "remaining": 4,
        "total": 4
      }
    ]
  },
  {
    "name": "25X THE CASH",
    "price": 10.0,
    "totalTickets": 3414331,
    "remainingTickets": 471177,
    "gameNumber": "586",
    "tiers": [
      {
        "prize": 10000,
        "remaining": 1,
        "total": 1
      }
    ]
  },
  {
    "name": "CASH DOUBLE DOUBLER",
    "price": 10.0,
    "totalTickets": 1796964,
    "remainingTickets": 165320,
    "gameNumber": "632",
    "tiers": [
      {
        "prize": 5000,
        "remaining": 1,
        "total": 1
      }
    ]
  },
  {
    "name": "MONEY CRAZE",
    "price": 10.0,
    "totalTickets": 0,
    "remainingTickets": 0,
    "gameNumber": "651",
    "tiers": [
      {
        "prize": 1000,
        "remaining": 5,
        "total": 5
      }
    ]
  },
  {
    "name": "ULTIMATE BONUS PAYOUT",
    "price": 10.0,
    "totalTickets": 1809937,
    "remainingTickets": 88686,
    "gameNumber": "660",
    "tiers": [
      {
        "prize": 5000,
        "remaining": 2,
        "total": 2
      }
    ]
  },
  {
    "name": "CASH TIMES 10",
    "price": 10.0,
    "totalTickets": 1894731,
    "remainingTickets": 325893,
    "gameNumber": "674",
    "tiers": [
      {
        "prize": 250000,
        "remaining": 1,
        "total": 1
      }
    ]
  },
  {
    "name": "BLAZING BUCKS",
    "price": 10.0,
    "totalTickets": 1749285,
    "remainingTickets": 570266,
    "gameNumber": "677",
    "tiers": [
      {
        "prize": 250000,
        "remaining": 1,
        "total": 1
      }
    ]
  },
  {
    "name": "25X THE WIN",
    "price": 10.0,
    "totalTickets": 1870108,
    "remainingTickets": 1024819,
    "gameNumber": "686",
    "tiers": [
      {
        "prize": 250000,
        "remaining": 2,
        "total": 2
      }
    ]
  },
  {
    "name": "JURASSIC PARK",
    "price": 10.0,
    "totalTickets": 3248299,
    "remainingTickets": 1032959,
    "gameNumber": "693",
    "tiers": [
      {
        "prize": 250000,
        "remaining": 3,
        "total": 3
      }
    ]
  },
  {
    "name": "HOLIDAY $1,000S",
    "price": 10.0,
    "totalTickets": 1043390,
    "remainingTickets": 202417,
    "gameNumber": "703",
    "tiers": [
      {
        "prize": 1000,
        "remaining": 470,
        "total": 470
      }
    ]
  },
  {
    "name": "HAMILTON",
    "price": 10.0,
    "totalTickets": 1639467,
    "remainingTickets": 739399,
    "gameNumber": "711",
    "tiers": [
      {
        "prize": 250000,
        "remaining": 2,
        "total": 2
      }
    ]
  },
  {
    "name": "$500,000 ROYAL CASH",
    "price": 20.0,
    "totalTickets": 1627104,
    "remainingTickets": 268472,
    "gameNumber": "630",
    "tiers": [
      {
        "prize": 500000,
        "remaining": 2,
        "total": 2
      }
    ]
  },
  {
    "name": "$50,000 BANKROLL",
    "price": 20.0,
    "totalTickets": 1752620,
    "remainingTickets": 112167,
    "gameNumber": "661",
    "tiers": [
      {
        "prize": 50000,
        "remaining": 3,
        "total": 3
      }
    ]
  },
  {
    "name": "CASH BONANZA",
    "price": 20.0,
    "totalTickets": 1188352,
    "remainingTickets": 267379,
    "gameNumber": "667",
    "tiers": [
      {
        "prize": 50000,
        "remaining": 1,
        "total": 1
      }
    ]
  },
  {
    "name": "MAINE MILLIONS",
    "price": 30.0,
    "totalTickets": 3585611,
    "remainingTickets": 315533,
    "gameNumber": "655",
    "tiers": [
      {
        "prize": 100000,
        "remaining": 2,
        "total": 2
      }
    ]
  },
  {
    "name": "$70 MILLION SUPREME",
    "price": 30.0,
    "totalTickets": 4083620,
    "remainingTickets": 3230143,
    "gameNumber": "718",
    "tiers": [
      {
        "prize": 1000000,
        "remaining": 4,
        "total": 4
      }
    ]
  }
]