[
  {
    "name": "Top line",
    "price": 20.0,
    "totalTickets": 0,
    "remainingTickets": 0,
    "gameNumber": "557",
    "tiers": [
      {
        "prize": 2000000,
        "remaining": 2,
        "total": 2
      },
      {
        "prize": 100000,
        "remaining": 3,
        "total": 4
      },
      {
        "prize": 20000,
        "remaining": 5,
        "total": 5
      },
      {
        "prize": 10000,
        "remaining": 10,
        "total": 11
      },
      {
        "prize": 5000,
        "remaining": 25,
        "total": 25
      },
      {
        "prize": 1000,
        "remaining": 1073,
        "total": 1108
      },
      {
        "prize": 500,
        "remaining": 1702,
        "total": 1806
      },
      {
        "prize": 200,
        "remaining": 5163,
        "total": 5458
      },
      {
        "prize": 100,
        "remaining": 129465,
        "total": 136475
      },
      {
        "prize": 50,
        "remaining": 133235,
        "total": 140460
      },
      {
        "prize": 40,
        "remaining": 310577,
        "total": 327381
      },
      {
        "prize": 20,
        "remaining": 440296,
        "total": 463855
      }
    ],
    "imageUrl": "https://www.molottery.com/media/scratchers/tile/557.png"
  },
  {
    "name": "Top line",
    "price": 5.0,
    "totalTickets": 0,
    "remainingTickets": 0,
    "gameNumber": "559",
    "tiers": [
      {
        "prize": 100000,
        "remaining": 5,
        "total": 5
      },
      {
        "prize": 20000,
        "remaining": 8,
        "total": 9
      },
      {
        "prize": 5000,
        "remaining": 23,
        "total": 26
      },
      {
        "prize": 1000,
        "remaining": 144,
        "total": 153
      },
      {
        "prize": 500,
        "remaining": 157,
        "total": 176
      },
      {
        "prize": 200,
        "remaining": 636,
        "total": 701
      },
      {
        "prize": 100,
        "remaining": 12214,
        "total": 13455
      },
      {
        "prize": 75,
        "remaining": 2541,
        "total": 2802
      },
      {
        "prize": 50,
        "remaining": 9534,
        "total": 10486
      },
      {
        "prize": 40,
        "remaining": 31630,
        "total": 34931
      },
      {
        "prize": 25,
        "remaining": 31657,
        "total": 34764
      },
      {
        "prize": 20,
        "remaining": 95134,
        "total": 104585
      },
      {
        "prize": 10,
        "remaining": 603584,
        "total": 661975
      }
    ],
    "imageUrl": "https://www.molottery.com/media/scratchers/tile/559.png"
  },
  {
    "name": "Top line",
    "price": 2.0,
    "totalTickets": 0,
    "remainingTickets": 0,
    "gameNumber": "558",
    "tiers": [
      {
        "prize": 25000,
        "remaining": 3,
        "total": 5
      },
      {
        "prize": 5000,
        "remaining": 4,
        "total": 8
      },
      {
        "prize": 1000,
        "remaining": 63,
        "total": 88
      },
      {
        "prize": 500,
        "remaining": 643,
        "total": 908
      },
      {
        "prize": 100,
        "remaining": 5027,
        "total": 7077
      },
      {
        "prize": 50,
        "remaining": 10297,
        "total": 14424
      },
      {
        "prize": 20,
        "remaining": 25363,
        "total": 35400
      },
      {
        "prize": 10,
        "remaining": 76679,
        "total": 106200
      },
      {
        "prize": 5,
        "remaining": 77440,
        "total": 106200
      },
      {
        "prize": 4,
        "remaining": 286075,
        "total": 389398
      },
      {
        "prize": 2,
        "remaining": 393355,
        "total": 531004
      }
    ],
    "imageUrl": "https://www.molottery.com/media/scratchers/tile/558.png"
  },
  {
    "name": "Top line",
    "price": 10.0,
    "totalTickets": 0,
    "remainingTickets": 0,
    "gameNumber": "555",
    "tiers": [
      {
        "prize": 250000,
        "remaining": 2,
        "total": 3
      },
      {
        "prize": 25000,
        "remaining": 4,
        "total": 8
      },
      {
        "prize": 2026,
        "remaining": 15,
        "total": 24
      },
      {
        "prize": 1776,
        "remaining": 131,
        "total": 247
      },
      {
        "prize": 250,
        "remaining": 2649,
        "total": 5234
      },
      {
        "prize": 100,
        "remaining": 20504,
        "total": 40644
      },
      {
        "prize": 50,
        "remaining": 21231,
        "total": 41951
      },
      {
        "prize": 30,
        "remaining": 10685,
        "total": 20986
      },
      {
        "prize": 25,
        "remaining": 12239,
        "total": 23824
      },
      {
        "prize": 20,
        "remaining": 86042,
        "total": 167804
      },
      {
        "prize": 15,
        "remaining": 65349,
        "total": 125853
      },
      {
        "prize": 10,
        "remaining": 175443,
        "total": 335608
      }
    ],
    "imageUrl": "https://www.molottery.com/media/scratchers/tile/555.png"
  },
  {
    "name": "Top line",
    "price": 5.0,
    "totalTickets": 0,
    "remainingTickets": 0,
    "gameNumber": "556",
    "tiers": [
      {
        "prize": 100000,
        "remaining": 5,
        "total": 6
      },
      {
        "prize": 20000,
        "remaining": 5,
        "total": 6
      },
      {
        "prize": 5000,
        "remaining": 22,
        "total": 29
      },
      {
        "prize": 1000,
        "remaining": 560,
        "total": 720
      },
      {
        "prize": 500,
        "remaining": 138,
        "total": 184
      },
      {
        "prize": 200,
        "remaining": 699,
        "total": 911
      },
      {
        "prize": 100,
        "remaining": 15397,
        "total": 20555
      },
      {
        "prize": 75,
        "remaining": 2760,
        "total": 3690
      },
      {
        "prize": 50,
        "remaining": 10397,
        "total": 13880
      },
      {
        "prize": 40,
        "remaining": 34777,
        "total": 46208
      },
      {
        "prize": 25,
        "remaining": 25303,
        "total": 33429
      },
      {
        "prize": 20,
        "remaining": 52263,
        "total": 69059
      },
      {
        "prize": 15,
        "remaining": 208916,
        "total": 276485
      },
      {
        "prize": 10,
        "remaining": 209861,
        "total": 276386
      },
      {
        "prize": 5,
        "remaining": 496626,
        "total": 644812
      }
    ],
    "imageUrl": "https://www.molottery.com/media/scratchers/tile/556.png"
  },
  {
    "name": "Top line",
    "price": 1.0,
    "totalTickets": 0,
    "remainingTickets": 0,
    "gameNumber": "566",
    "tiers": [
      {
        "prize": 7777,
        "remaining": 4,
        "total": 6
      },
      {
        "prize": 1000,
        "remaining": 5,
        "total": 6
      },
      {
        "prize": 777,
        "remaining": 25,
        "total": 34
      },
      {
        "prize": 500,
        "remaining": 33,
        "total": 48
      },
      {
        "prize": 100,
        "remaining": 1443,
        "total": 2051
      },
      {
        "prize": 50,
        "remaining": 3394,
        "total": 4743
      },
      {
        "prize": 30,
        "remaining": 8097,
        "total": 11277
      },
      {
        "prize": 25,
        "remaining": 19472,
        "total": 27129
      },
      {
        "prize": 10,
        "remaining": 63806,
        "total": 88176
      },
      {
        "prize": 7,
        "remaining": 39488,
        "total": 54258
      },
      {
        "prize": 5,
        "remaining": 79135,
        "total": 108516
      },
      {
        "prize": 4,
        "remaining": 39772,
        "total": 54260
      },
      {
        "prize": 3,
        "remaining": 39825,
        "total": 54216
      },
      {
        "prize": 2,
        "remaining": 281222,
        "total": 379830
      },
      {
        "prize": 1,
        "remaining": 700760,
        "total": 935953
      }
    ],
    "imageUrl": "https://www.molottery.com/media/scratchers/tile/566.png"
  },
  {
    "name": "Top line",
    "price": 5.0,
    "totalTickets": 0,
    "remainingTickets": 0,
    "gameNumber": "560",
    "tiers": [
      {
        "prize": 100005,
        "remaining": 3,
        "total": 4
      },
      {
        "prize": 20175,
        "remaining": 2,
        "total": 3
      },
      {
        "prize": 10100,
        "remaining": 3,
        "total": 3
      },
      {
        "prize": 5120,
        "remaining": 6,
        "total": 8
      },
      {
        "prize": 2510,
        "remaining": 3,
        "total": 5
      },
      {
        "prize": 2500,
        "remaining": 4,
        "total": 5
      },
      {
        "prize": 1010,
        "remaining": 12,
        "total": 15
      },
      {
        "prize": 1000,
        "remaining": 38,
        "total": 50
      },
      {
        "prize": 505,
        "remaining": 249,
        "total": 322
      },
      {
        "prize": 500,
        "remaining": 168,
        "total": 219
      },
      {
        "prize": 205,
        "remaining": 456,
        "total": 584
      },
      {
        "prize": 200,
        "remaining": 498,
        "total": 648
      },
      {
        "prize": 180,
        "remaining": 567,
        "total": 723
      },
      {
        "prize": 125,
        "remaining": 1119,
        "total": 1440
      },
      {
        "prize": 105,
        "remaining": 2727,
        "total": 3552
      },
      {
        "prize": 100,
        "remaining": 2747,
        "total": 3582
      },
      {
        "prize": 80,
        "remaining": 569,
        "total": 724
      },
      {
        "prize": 75,
        "remaining": 1090,
        "total": 1419
      },
      {
        "prize": 60,
        "remaining": 5525,
        "total": 7167
      },
      {
        "prize": 55,
        "remaining": 2770,
        "total": 3578
      },
      {
        "prize": 50,
        "remaining": 20335,
        "total": 26413
      },
      {
        "prize": 30,
        "remaining": 8872,
        "total": 11389
      },
      {
        "prize": 25,
        "remaining": 45587,
        "total": 58829
      },
      {
        "prize": 20,
        "remaining": 69597,
        "total": 89099
      },
      {
        "prize": 15,
        "remaining": 42006,
        "total": 53467
      },
      {
        "prize": 10,
        "remaining": 265577,
        "total": 338575
      },
      {
        "prize": 5,
        "remaining": 406470,
        "total": 516773
      }
    ],
    "imageUrl": "https://www.molottery.com/media/scratchers/tile/560.png"
  },
  {
    "name": "Top line",
    "price": 5.0,
    "totalTickets": 0,
    "remainingTickets": 0,
    "gameNumber": "552",
    "tiers": [
      {
        "prize": 500,
        "remaining": 841,
        "total": 2275
      },
      {
        "prize": 100,
        "remaining": 1105,
        "total": 2987
      },
      {
        "prize": 75,
        "remaining": 2109,
        "total": 5686
      },
      {
        "prize": 50,
        "remaining": 6985,
        "total": 18894
      },
      {
        "prize": 25,
        "remaining": 14142,
        "total": 37789
      },
      {
        "prize": 15,
        "remaining": 14402,
        "total": 37789
      },
      {
        "prize": 10,
        "remaining": 87984,
        "total": 226779
      },
      {
        "prize": 5,
        "remaining": 92422,
        "total": 226644
      }
    ],
    "imageUrl": "https://www.molottery.com/media/scratchers/tile/552.png"
  },
  {
    "name": "Top line",
    "price": 10.0,
    "totalTickets": 0,
    "remainingTickets": 0,
    "gameNumber": "550",
    "tiers": [
      {
        "prize": 250000,
        "remaining": 4,
        "total": 5
      },
      {
        "prize": 25000,
        "remaining": 8,
        "total": 10
      },
      {
        "prize": 5000,
        "remaining": 39,
        "total": 46
      },
      {
        "prize": 1000,
        "remaining": 561,
        "total": 650
      },
      {
        "prize": 500,
        "remaining": 1224,
        "total": 1498
      },
      {
        "prize": 200,
        "remaining": 3540,
        "total": 4284
      },
      {
        "prize": 100,
        "remaining": 58942,
        "total": 71307
      },
      {
        "prize": 50,
        "remaining": 59002,
        "total": 71307
      },
      {
        "prize": 30,
        "remaining": 67958,
        "total": 82007
      },
      {
        "prize": 20,
        "remaining": 310814,
        "total": 374368
      },
      {
        "prize": 10,
        "remaining": 597573,
        "total": 713101
      }
    ],
    "imageUrl": "https://www.molottery.com/media/scratchers/tile/550.png"
  },
  {
    "name": "Top line",
    "price": 1.0,
    "totalTickets": 0,
    "remainingTickets": 0,
    "gameNumber": "553",
    "tiers": [
      {
        "prize": 2500,
        "remaining": 5,
        "total": 7
      },
      {
        "prize": 1000,
        "remaining": 8,
        "total": 11
      },
      {
        "prize": 500,
        "remaining": 10,
        "total": 17
      },
      {
        "prize": 100,
        "remaining": 1381,
        "total": 2116
      },
      {
        "prize": 40,
        "remaining": 20328,
        "total": 30932
      },
      {
        "prize": 20,
        "remaining": 18561,
        "total": 28102
      },
      {
        "prize": 10,
        "remaining": 46701,
        "total": 70238
      },
      {
        "prize": 5,
        "remaining": 37645,
        "total": 56210
      },
      {
        "prize": 4,
        "remaining": 132563,
        "total": 196742
      },
      {
        "prize": 2,
        "remaining": 287121,
        "total": 421558
      },
      {
        "prize": 1,
        "remaining": 657283,
        "total": 955440
      }
    ],
    "imageUrl": "https://www.molottery.com/media/scratchers/tile/553.png"
  },
  {
    "name": "Top line",
    "price": 5.0,
    "totalTickets": 0,
    "remainingTickets": 0,
    "gameNumber": "546",
    "tiers": [
      {
        "prize": 77777,
        "remaining": 3,
        "total": 5
      },
      {
        "prize": 10000,
        "remaining": 0,
        "total": 4
      },
      {
        "prize": 7777,
        "remaining": 5,
        "total": 12
      },
      {
        "prize": 1000,
        "remaining": 7,
        "total": 17
      },
      {
        "prize": 777,
        "remaining": 105,
        "total": 228
      },
      {
        "prize": 500,
        "remaining": 80,
        "total": 177
      },
      {
        "prize": 277,
        "remaining": 113,
        "total": 276
      },
      {
        "prize": 77,
        "remaining": 18852,
        "total": 43450
      },
      {
        "prize": 27,
        "remaining": 35343,
        "total": 81102
      },
      {
        "prize": 17,
        "remaining": 30373,
        "total": 69027
      },
      {
        "prize": 15,
        "remaining": 60673,
        "total": 138054
      },
      {
        "prize": 10,
        "remaining": 92423,
        "total": 207021
      },
      {
        "prize": 5,
        "remaining": 219115,
        "total": 483309
      }
    ],
    "imageUrl": "https://www.molottery.com/media/scratchers/tile/546.png"
  },
  {
    "name": "Top line",
    "price": 2.0,
    "totalTickets": 0,
    "remainingTickets": 0,
    "gameNumber": "549",
    "tiers": [
      {
        "prize": 30000,
        "remaining": 3,
        "total": 5
      },
      {
        "prize": 3000,
        "remaining": 12,
        "total": 20
      },
      {
        "prize": 1000,
        "remaining": 42,
        "total": 72
      },
      {
        "prize": 500,
        "remaining": 161,
        "total": 296
      },
      {
        "prize": 100,
        "remaining": 4139,
        "total": 7956
      },
      {
        "prize": 40,
        "remaining": 20687,
        "total": 39827
      },
      {
        "prize": 20,
        "remaining": 15780,
        "total": 29898
      },
      {
        "prize": 15,
        "remaining": 21187,
        "total": 39827
      },
      {
        "prize": 10,
        "remaining": 32413,
        "total": 59706
      },
      {
        "prize": 5,
        "remaining": 66626,
        "total": 119439
      },
      {
        "prize": 4,
        "remaining": 176898,
        "total": 318567
      },
      {
        "prize": 2,
        "remaining": 415631,
        "total": 716984
      }
    ],
    "imageUrl": "https://www.molottery.com/media/scratchers/tile/549.png"
  },
  {
    "name": "Top line",
    "price": 20.0,
    "totalTickets": 0,
    "remainingTickets": 0,
    "gameNumber": "538",
    "tiers": [
      {
        "prize": 2000000,
        "remaining": 1,
        "total": 2
      },
      {
        "prize": 100000,
        "remaining": 1,
        "total": 3
      },
      {
        "prize": 20000,
        "remaining": 2,
        "total": 4
      },
      {
        "prize": 10000,
        "remaining": 7,
        "total": 10
      },
      {
        "prize": 5000,
        "remaining": 18,
        "total": 25
      },
      {
        "prize": 1000,
        "remaining": 624,
        "total": 905
      },
      {
        "prize": 500,
        "remaining": 3721,
        "total": 5462
      },
      {
        "prize": 300,
        "remaining": 3708,
        "total": 5461
      },
      {
        "prize": 200,
        "remaining": 11096,
        "total": 16324
      },
      {
        "prize": 100,
        "remaining": 74083,
        "total": 108765
      },
      {
        "prize": 50,
        "remaining": 73872,
        "total": 108765
      },
      {
        "prize": 40,
        "remaining": 184761,
        "total": 271924
      },
      {
        "prize": 20,
        "remaining": 353015,
        "total": 516639
      }
    ],
    "imageUrl": "https://www.molottery.com/media/scratchers/tile/538.png"
  },
  {
    "name": "Top line",
    "price": 50.0,
    "totalTickets": 0,
    "remainingTickets": 0,
    "gameNumber": "554",
    "tiers": [
      {
        "prize": 5000000,
        "remaining": 2,
        "total": 3
      },
      {
        "prize": 1000000,
        "remaining": 3,
        "total": 3
      },
      {
        "prize": 50000,
        "remaining": 45,
        "total": 50
      },
      {
        "prize": 10000,
        "remaining": 232,
        "total": 260
      },
      {
        "prize": 5000,
        "remaining": 650,
        "total": 728
      },
      {
        "prize": 1000,
        "remaining": 2372,
        "total": 2637
      },
      {
        "prize": 500,
        "remaining": 113146,
        "total": 127545
      },
      {
        "prize": 200,
        "remaining": 123609,
        "total": 139441
      },
      {
        "prize": 100,
        "remaining": 705690,
        "total": 795758
      },
      {
        "prize": 75,
        "remaining": 470731,
        "total": 530506
      },
      {
        "prize": 50,
        "remaining": 353176,
        "total": 397869
      }
    ],
    "imageUrl": "https://www.molottery.com/media/scratchers/tile/554.png"
  },
  {
    "name": "Top line",
    "price": 5.0,
    "totalTickets": 0,
    "remainingTickets": 0,
    "gameNumber": "544",
    "tiers": [
      {
        "prize": 100000,
        "remaining": 2,
        "total": 4
      },
      {
        "prize": 10000,
        "remaining": 16,
        "total": 27
      },
      {
        "prize": 1000,
        "remaining": 276,
        "total": 524
      },
      {
        "prize": 500,
        "remaining": 76,
        "total": 151
      },
      {
        "prize": 200,
        "remaining": 303,
        "total": 603
      },
      {
        "prize": 100,
        "remaining": 5989,
        "total": 11827
      },
      {
        "prize": 75,
        "remaining": 1260,
        "total": 2461
      },
      {
        "prize": 50,
        "remaining": 4777,
        "total": 9293
      },
      {
        "prize": 40,
        "remaining": 15723,
        "total": 30817
      },
      {
        "prize": 25,
        "remaining": 9414,
        "total": 18425
      },
      {
        "prize": 20,
        "remaining": 23964,
        "total": 46188
      },
      {
        "prize": 15,
        "remaining": 95550,
        "total": 184898
      },
      {
        "prize": 10,
        "remaining": 97335,
        "total": 184857
      },
      {
        "prize": 5,
        "remaining": 229467,
        "total": 431315
      }
    ],
    "imageUrl": "https://www.molottery.com/media/scratchers/tile/544.png"
  },
  {
    "name": "Top line",
    "price": 10.0,
    "totalTickets": 0,
    "remainingTickets": 0,
    "gameNumber": "526",
    "tiers": [
      {
        "prize": 1000000,
        "remaining": 1,
        "total": 2
      },
      {
        "prize": 100000,
        "remaining": 1,
        "total": 4
      },
      {
        "prize": 10000,
        "remaining": 7,
        "total": 16
      },
      {
        "prize": 1000,
        "remaining": 138,
        "total": 262
      },
      {
        "prize": 500,
        "remaining": 188,
        "total": 363
      },
      {
        "prize": 250,
        "remaining": 1348,
        "total": 2647
      },
      {
        "prize": 100,
        "remaining": 5202,
        "total": 10166
      },
      {
        "prize": 75,
        "remaining": 77335,
        "total": 151644
      },
      {
        "prize": 25,
        "remaining": 84075,
        "total": 162725
      },
      {
        "prize": 15,
        "remaining": 270529,
        "total": 517790
      },
      {
        "prize": 10,
        "remaining": 311514,
        "total": 591760
      }
    ],
    "imageUrl": "https://www.molottery.com/media/scratchers/tile/526.png"
  },
  {
    "name": "Top line",
    "price": 50.0,
    "totalTickets": 0,
    "remainingTickets": 0,
    "gameNumber": "576",
    "tiers": [
      {
        "prize": 1000000,
        "remaining": 12,
        "total": 15
      },
      {
        "prize": 50000,
        "remaining": 33,
        "total": 40
      },
      {
        "prize": 10000,
        "remaining": 216,
        "total": 250
      },
      {
        "prize": 5000,
        "remaining": 634,
        "total": 734
      },
      {
        "prize": 1000,
        "remaining": 2260,
        "total": 2603
      },
      {
        "prize": 500,
        "remaining": 89677,
        "total": 104409
      },
      {
        "prize": 200,
        "remaining": 198954,
        "total": 231863
      },
      {
        "prize": 100,
        "remaining": 447134,
        "total": 521062
      },
      {
        "prize": 75,
        "remaining": 894569,
        "total": 1042124
      }
    ],
    "imageUrl": "https://www.molottery.com/media/scratchers/tile/576.png"
  },
  {
    "name": "Top line",
    "price": 10.0,
    "totalTickets": 0,
    "remainingTickets": 0,
    "gameNumber": "524",
    "tiers": [
      {
        "prize": 100,
        "remaining": 61948,
        "total": 83991
      },
      {
        "prize": 50,
        "remaining": 274976,
        "total": 372009
      }
    ],
    "imageUrl": "https://www.molottery.com/media/scratchers/tile/524.png"
  },
  {
    "name": "Top line",
    "price": 1.0,
    "totalTickets": 0,
    "remainingTickets": 0,
    "gameNumber": "545",
    "tiers": [
      {
        "prize": 5000,
        "remaining": 0,
        "total": 6
      },
      {
        "prize": 1000,
        "remaining": 3,
        "total": 10
      },
      {
        "prize": 500,
        "remaining": 4,
        "total": 14
      },
      {
        "prize": 100,
        "remaining": 401,
        "total": 1855
      },
      {
        "prize": 25,
        "remaining": 5835,
        "total": 25000
      },
      {
        "prize": 20,
        "remaining": 6757,
        "total": 28586
      },
      {
        "prize": 10,
        "remaining": 19504,
        "total": 79988
      },
      {
        "prize": 5,
        "remaining": 11786,
        "total": 45720
      },
      {
        "prize": 4,
        "remaining": 42012,
        "total": 160020
      },
      {
        "prize": 2,
        "remaining": 94299,
        "total": 342900
      },
      {
        "prize": 1,
        "remaining": 239057,
        "total": 800100
      }
    ],
    "imageUrl": "https://www.molottery.com/media/scratchers/tile/545.png"
  },
  {
    "name": "Top line",
    "price": 5.0,
    "totalTickets": 0,
    "remainingTickets": 0,
    "gameNumber": "536",
    "tiers": [
      {
        "prize": 138889,
        "remaining": 1,
        "total": 5
      },
      {
        "prize": 25000,
        "remaining": 1,
        "total": 3
      },
      {
        "prize": 2500,
        "remaining": 8,
        "total": 17
      },
      {
        "prize": 500,
        "remaining": 53,
        "total": 141
      },
      {
        "prize": 100,
        "remaining": 6016,
        "total": 13750
      },
      {
        "prize": 50,
        "remaining": 22535,
        "total": 51524
      },
      {
        "prize": 25,
        "remaining": 22983,
        "total": 51572
      },
      {
        "prize": 15,
        "remaining": 61482,
        "total": 137425
      },
      {
        "prize": 10,
        "remaining": 155787,
        "total": 343670
      },
      {
        "prize": 5,
        "remaining": 234441,
        "total": 498343
      }
    ],
    "imageUrl": "https://www.molottery.com/media/scratchers/tile/536.png"
  },
  {
    "name": "Top line",
    "price": 2.0,
    "totalTickets": 0,
    "remainingTickets": 0,
    "gameNumber": "537",
    "tiers": [
      {
        "prize": 25000,
        "remaining": 2,
        "total": 5
      },
      {
        "prize": 5000,
        "remaining": 3,
        "total": 8
      },
      {
        "prize": 1000,
        "remaining": 34,
        "total": 88
      },
      {
        "prize": 500,
        "remaining": 293,
        "total": 891
      },
      {
        "prize": 100,
        "remaining": 2519,
        "total": 7137
      },
      {
        "prize": 50,
        "remaining": 5000,
        "total": 14556
      },
      {
        "prize": 20,
        "remaining": 12583,
        "total": 35695
      },
      {
        "prize": 10,
        "remaining": 38696,
        "total": 107085
      },
      {
        "prize": 5,
        "remaining": 39808,
        "total": 107085
      },
      {
        "prize": 4,
        "remaining": 146203,
        "total": 392643
      },
      {
        "prize": 2,
        "remaining": 208830,
        "total": 535429
      }
    ],
    "imageUrl": "https://www.molottery.com/media/scratchers/tile/537.png"
  },
  {
    "name": "Top line",
    "price": 20.0,
    "totalTickets": 0,
    "remainingTickets": 0,
    "gameNumber": "539",
    "tiers": [
      {
        "prize": 2000000,
        "remaining": 0,
        "total": 2
      },
      {
        "prize": 100000,
        "remaining": 1,
        "total": 2
      },
      {
        "prize": 86000,
        "remaining": 2,
        "total": 4
      },
      {
        "prize": 20000,
        "remaining": 2,
        "total": 5
      },
      {
        "prize": 10000,
        "remaining": 4,
        "total": 11
      },
      {
        "prize": 5000,
        "remaining": 9,
        "total": 25
      },
      {
        "prize": 1000,
        "remaining": 461,
        "total": 1116
      },
      {
        "prize": 400,
        "remaining": 817,
        "total": 2154
      },
      {
        "prize": 200,
        "remaining": 2107,
        "total": 5444
      },
      {
        "prize": 100,
        "remaining": 79260,
        "total": 206282
      },
      {
        "prize": 40,
        "remaining": 115301,
        "total": 299592
      },
      {
        "prize": 20,
        "remaining": 201662,
        "total": 517099
      }
    ],
    "imageUrl": "https://www.molottery.com/media/scratchers/tile/539.png"
  },
  {
    "name": "Top line",
    "price": 10.0,
    "totalTickets": 0,
    "remainingTickets": 0,
    "gameNumber": "540",
    "tiers": [
      {
        "prize": 1000000,
        "remaining": 1,
        "total": 2
      },
      {
        "prize": 50000,
        "remaining": 3,
        "total": 5
      },
      {
        "prize": 5000,
        "remaining": 27,
        "total": 50
      },
      {
        "prize": 1000,
        "remaining": 926,
        "total": 1595
      },
      {
        "prize": 200,
        "remaining": 2615,
        "total": 4607
      },
      {
        "prize": 100,
        "remaining": 26451,
        "total": 46155
      },
      {
        "prize": 50,
        "remaining": 87992,
        "total": 153888
      },
      {
        "prize": 25,
        "remaining": 44158,
        "total": 76944
      },
      {
        "prize": 20,
        "remaining": 176563,
        "total": 307776
      },
      {
        "prize": 15,
        "remaining": 133284,
        "total": 230832
      },
      {
        "prize": 10,
        "remaining": 357415,
        "total": 615552
      }
    ],
    "imageUrl": "https://www.molottery.com/media/scratchers/tile/540.png"
  },
  {
    "name": "Top line",
    "price": 5.0,
    "totalTickets": 0,
    "remainingTickets": 0,
    "gameNumber": "541",
    "tiers": [
      {
        "prize": 100000,
        "remaining": 1,
        "total": 4
      },
      {
        "prize": 10000,
        "remaining": 0,
        "total": 6
      },
      {
        "prize": 1000,
        "remaining": 6,
        "total": 30
      },
      {
        "prize": 500,
        "remaining": 372,
        "total": 2527
      },
      {
        "prize": 100,
        "remaining": 1592,
        "total": 10545
      },
      {
        "prize": 50,
        "remaining": 6133,
        "total": 37781
      },
      {
        "prize": 25,
        "remaining": 10460,
        "total": 62946
      },
      {
        "prize": 15,
        "remaining": 20746,
        "total": 125892
      },
      {
        "prize": 10,
        "remaining": 47332,
        "total": 267484
      },
      {
        "prize": 5,
        "remaining": 82269,
        "total": 409222
      }
    ],
    "imageUrl": "https://www.molottery.com/media/scratchers/tile/541.png"
  },
  {
    "name": "Top line",
    "price": 2.0,
    "totalTickets": 0,
    "remainingTickets": 0,
    "gameNumber": "542",
    "tiers": [
      {
        "prize": 25000,
        "remaining": 2,
        "total": 5
      },
      {
        "prize": 2500,
        "remaining": 3,
        "total": 5
      },
      {
        "prize": 1000,
        "remaining": 12,
        "total": 24
      },
      {
        "prize": 100,
        "remaining": 7179,
        "total": 13954
      },
      {
        "prize": 40,
        "remaining": 10360,
        "total": 19592
      },
      {
        "prize": 25,
        "remaining": 18072,
        "total": 33546
      },
      {
        "prize": 10,
        "remaining": 36936,
        "total": 67092
      },
      {
        "prize": 5,
        "remaining": 54692,
        "total": 100638
      },
      {
        "prize": 4,
        "remaining": 154578,
        "total": 285164
      },
      {
        "prize": 2,
        "remaining": 324523,
        "total": 587032
      }
    ],
    "imageUrl": "https://www.molottery.com/media/scratchers/tile/542.png"
  },
  {
    "name": "Top line",
    "price": 1.0,
    "totalTickets": 0,
    "remainingTickets": 0,
    "gameNumber": "543",
    "tiers": [
      {
        "prize": 2500,
        "remaining": 0,
        "total": 6
      },
      {
        "prize": 1000,
        "remaining": 2,
        "total": 8
      },
      {
        "prize": 500,
        "remaining": 1,
        "total": 12
      },
      {
        "prize": 100,
        "remaining": 205,
        "total": 1466
      },
      {
        "prize": 50,
        "remaining": 2759,
        "total": 19834
      },
      {
        "prize": 15,
        "remaining": 2826,
        "total": 18025
      },
      {
        "prize": 10,
        "remaining": 7349,
        "total": 31512
      },
      {
        "prize": 5,
        "remaining": 6004,
        "total": 36074
      },
      {
        "prize": 4,
        "remaining": 22326,
        "total": 126254
      },
      {
        "prize": 2,
        "remaining": 53287,
        "total": 270296
      },
      {
        "prize": 1,
        "remaining": 138996,
        "total": 621902
      }
    ],
    "imageUrl": "https://www.molottery.com/media/scratchers/tile/543.png"
  },
  {
    "name": "Top line",
    "price": 3.0,
    "totalTickets": 0,
    "remainingTickets": 0,
    "gameNumber": "528",
    "tiers": [
      {
        "prize": 50000,
        "remaining": 5,
        "total": 10
      },
      {
        "prize": 5000,
        "remaining": 13,
        "total": 28
      },
      {
        "prize": 1000,
        "remaining": 60,
        "total": 115
      },
      {
        "prize": 500,
        "remaining": 284,
        "total": 568
      },
      {
        "prize": 100,
        "remaining": 4319,
        "total": 8650
      },
      {
        "prize": 60,
        "remaining": 4204,
        "total": 8413
      },
      {
        "prize": 50,
        "remaining": 5650,
        "total": 11233
      },
      {
        "prize": 20,
        "remaining": 34266,
        "total": 67405
      },
      {
        "prize": 12,
        "remaining": 61210,
        "total": 117952
      },
      {
        "prize": 10,
        "remaining": 78216,
        "total": 151611
      },
      {
        "prize": 6,
        "remaining": 370636,
        "total": 691058
      },
      {
        "prize": 3,
        "remaining": 374383,
        "total": 673957
      }
    ],
    "imageUrl": "https://www.molottery.com/media/scratchers/tile/528.png"
  },
  {
    "name": "Top line",
    "price": 5.0,
    "totalTickets": 0,
    "remainingTickets": 0,
    "gameNumber": "533",
    "tiers": [
      {
        "prize": 100000,
        "remaining": 4,
        "total": 8
      },
      {
        "prize": 10000,
        "remaining": 3,
        "total": 8
      },
      {
        "prize": 2500,
        "remaining": 19,
        "total": 32
      },
      {
        "prize": 1000,
        "remaining": 21,
        "total": 40
      },
      {
        "prize": 500,
        "remaining": 249,
        "total": 556
      },
      {
        "prize": 250,
        "remaining": 2519,
        "total": 5871
      },
      {
        "prize": 100,
        "remaining": 2447,
        "total": 5603
      },
      {
        "prize": 75,
        "remaining": 4830,
        "total": 11170
      },
      {
        "prize": 60,
        "remaining": 4849,
        "total": 11156
      },
      {
        "prize": 50,
        "remaining": 7022,
        "total": 16162
      },
      {
        "prize": 40,
        "remaining": 6053,
        "total": 13892
      },
      {
        "prize": 30,
        "remaining": 6780,
        "total": 15588
      },
      {
        "prize": 25,
        "remaining": 36564,
        "total": 83323
      },
      {
        "prize": 20,
        "remaining": 48658,
        "total": 111147
      },
      {
        "prize": 15,
        "remaining": 86000,
        "total": 194548
      },
      {
        "prize": 10,
        "remaining": 224059,
        "total": 500260
      },
      {
        "prize": 5,
        "remaining": 358601,
        "total": 777896
      }
    ],
    "imageUrl": "https://www.molottery.com/media/scratchers/tile/533.png"
  },
  {
    "name": "Top line",
    "price": 5.0,
    "totalTickets": 0,
    "remainingTickets": 0,
    "gameNumber": "527",
    "tiers": [
      {
        "prize": 100000,
        "remaining": 2,
        "total": 6
      },
      {
        "prize": 20000,
        "remaining": 2,
        "total": 6
      },
      {
        "prize": 5000,
        "remaining": 8,
        "total": 29
      },
      {
        "prize": 1000,
        "remaining": 205,
        "total": 720
      },
      {
        "prize": 500,
        "remaining": 55,
        "total": 191
      },
      {
        "prize": 200,
        "remaining": 257,
        "total": 934
      },
      {
        "prize": 100,
        "remaining": 5538,
        "total": 20454
      },
      {
        "prize": 75,
        "remaining": 994,
        "total": 3707
      },
      {
        "prize": 50,
        "remaining": 3908,
        "total": 13954
      },
      {
        "prize": 40,
        "remaining": 12814,
        "total": 46173
      },
      {
        "prize": 25,
        "remaining": 9691,
        "total": 33463
      },
      {
        "prize": 20,
        "remaining": 19651,
        "total": 69105
      },
      {
        "prize": 15,
        "remaining": 78066,
        "total": 276610
      },
      {
        "prize": 10,
        "remaining": 80475,
        "total": 276476
      },
      {
        "prize": 5,
        "remaining": 204087,
        "total": 645198
      }
    ],
    "imageUrl": "https://www.molottery.com/media/scratchers/tile/527.png"
  },
  {
    "name": "Top line",
    "price": 30.0,
    "totalTickets": 0,
    "remainingTickets": 0,
    "gameNumber": "551",
    "tiers": [
      {
        "prize": 3000000,
        "remaining": 2,
        "total": 3
      },
      {
        "prize": 100000,
        "remaining": 2,
        "total": 3
      },
      {
        "prize": 25000,
        "remaining": 6,
        "total": 9
      },
      {
        "prize": 5000,
        "remaining": 40,
        "total": 62
      },
      {
        "prize": 2500,
        "remaining": 43,
        "total": 62
      },
      {
        "prize": 1000,
        "remaining": 1038,
        "total": 1546
      },
      {
        "prize": 500,
        "remaining": 7641,
        "total": 11820
      },
      {
        "prize": 200,
        "remaining": 23835,
        "total": 36955
      },
      {
        "prize": 100,
        "remaining": 166979,
        "total": 259113
      },
      {
        "prize": 60,
        "remaining": 372530,
        "total": 577430
      },
      {
        "prize": 50,
        "remaining": 286384,
        "total": 443861
      }
    ],
    "imageUrl": "https://www.molottery.com/media/scratchers/tile/551.png"
  },
  {
    "name": "Top line",
    "price": 10.0,
    "totalTickets": 0,
    "remainingTickets": 0,
    "gameNumber": "529",
    "tiers": [
      {
        "prize": 200000,
        "remaining": 1,
        "total": 2
      },
      {
        "prize": 20000,
        "remaining": 2,
        "total": 5
      },
      {
        "prize": 10000,
        "remaining": 4,
        "total": 20
      },
      {
        "prize": 5000,
        "remaining": 4,
        "total": 20
      },
      {
        "prize": 1000,
        "remaining": 252,
        "total": 810
      },
      {
        "prize": 500,
        "remaining": 634,
        "total": 1884
      },
      {
        "prize": 200,
        "remaining": 1776,
        "total": 5280
      },
      {
        "prize": 100,
        "remaining": 8503,
        "total": 25286
      },
      {
        "prize": 50,
        "remaining": 10472,
        "total": 30919
      },
      {
        "prize": 25,
        "remaining": 10379,
        "total": 30041
      },
      {
        "prize": 20,
        "remaining": 77794,
        "total": 225006
      },
      {
        "prize": 10,
        "remaining": 133110,
        "total": 374922
      }
    ],
    "imageUrl": "https://www.molottery.com/media/scratchers/tile/529.png"
  },
  {
    "name": "Top line",
    "price": 2.0,
    "totalTickets": 0,
    "remainingTickets": 0,
    "gameNumber": "534",
    "tiers": [
      {
        "prize": 25000,
        "remaining": 3,
        "total": 5
      },
      {
        "prize": 10000,
        "remaining": 2,
        "total": 5
      },
      {
        "prize": 1000,
        "remaining": 29,
        "total": 66
      },
      {
        "prize": 500,
        "remaining": 107,
        "total": 281
      },
      {
        "prize": 100,
        "remaining": 3044,
        "total": 7499
      },
      {
        "prize": 50,
        "remaining": 1674,
        "total": 4034
      },
      {
        "prize": 40,
        "remaining": 4561,
        "total": 11262
      },
      {
        "prize": 25,
        "remaining": 17534,
        "total": 41369
      },
      {
        "prize": 10,
        "remaining": 48879,
        "total": 110313
      },
      {
        "prize": 5,
        "remaining": 118468,
        "total": 257397
      },
      {
        "prize": 4,
        "remaining": 102413,
        "total": 220645
      },
      {
        "prize": 2,
        "remaining": 299087,
        "total": 625069
      }
    ],
    "imageUrl": "https://www.molottery.com/media/scratchers/tile/534.png"
  },
  {
    "name": "Top line",
    "price": 1.0,
    "totalTickets": 0,
    "remainingTickets": 0,
    "gameNumber": "535",
    "tiers": [
      {
        "prize": 1000,
        "remaining": 4,
        "total": 15
      },
      {
        "prize": 500,
        "remaining": 9,
        "total": 38
      },
      {
        "prize": 200,
        "remaining": 40,
        "total": 146
      },
      {
        "prize": 100,
        "remaining": 507,
        "total": 1764
      },
      {
        "prize": 40,
        "remaining": 2240,
        "total": 7155
      },
      {
        "prize": 20,
        "remaining": 11779,
        "total": 35614
      },
      {
        "prize": 10,
        "remaining": 50132,
        "total": 142400
      },
      {
        "prize": 5,
        "remaining": 53104,
        "total": 142404
      },
      {
        "prize": 3,
        "remaining": 89087,
        "total": 227873
      },
      {
        "prize": 2,
        "remaining": 131840,
        "total": 327626
      },
      {
        "prize": 1,
        "remaining": 423033,
        "total": 996917
      }
    ],
    "imageUrl": "https://www.molottery.com/media/scratchers/tile/535.png"
  },
  {
    "name": "Top line",
    "price": 5.0,
    "totalTickets": 0,
    "remainingTickets": 0,
    "gameNumber": "531",
    "tiers": [
      {
        "prize": 100000,
        "remaining": 1,
        "total": 3
      },
      {
        "prize": 20000,
        "remaining": 0,
        "total": 3
      },
      {
        "prize": 5000,
        "remaining": 0,
        "total": 11
      },
      {
        "prize": 1000,
        "remaining": 9,
        "total": 56
      },
      {
        "prize": 500,
        "remaining": 19,
        "total": 112
      },
      {
        "prize": 100,
        "remaining": 2397,
        "total": 12268
      },
      {
        "prize": 50,
        "remaining": 6649,
        "total": 32675
      },
      {
        "prize": 30,
        "remaining": 3215,
        "total": 16375
      },
      {
        "prize": 20,
        "remaining": 17944,
        "total": 81746
      },
      {
        "prize": 15,
        "remaining": 22839,
        "total": 108982
      },
      {
        "prize": 10,
        "remaining": 49823,
        "total": 217854
      },
      {
        "prize": 5,
        "remaining": 92806,
        "total": 381484
      }
    ],
    "imageUrl": "https://www.molottery.com/media/scratchers/tile/531.png"
  },
  {
    "name": "Top line",
    "price": 5.0,
    "totalTickets": 0,
    "remainingTickets": 0,
    "gameNumber": "530",
    "tiers": [
      {
        "prize": 100000,
        "remaining": 2,
        "total": 4
      },
      {
        "prize": 20000,
        "remaining": 2,
        "total": 4
      },
      {
        "prize": 5000,
        "remaining": 6,
        "total": 18
      },
      {
        "prize": 1000,
        "remaining": 39,
        "total": 72
      },
      {
        "prize": 500,
        "remaining": 112,
        "total": 249
      },
      {
        "prize": 100,
        "remaining": 5641,
        "total": 11719
      },
      {
        "prize": 50,
        "remaining": 27100,
        "total": 56061
      },
      {
        "prize": 25,
        "remaining": 15695,
        "total": 31869
      },
      {
        "prize": 15,
        "remaining": 60718,
        "total": 121268
      },
      {
        "prize": 10,
        "remaining": 154766,
        "total": 303169
      },
      {
        "prize": 5,
        "remaining": 226403,
        "total": 424440
      }
    ],
    "imageUrl": "https://www.molottery.com/media/scratchers/tile/530.png"
  },
  {
    "name": "Top line",
    "price": 20.0,
    "totalTickets": 0,
    "remainingTickets": 0,
    "gameNumber": "525",
    "tiers": [
      {
        "prize": 300000,
        "remaining": 1,
        "total": 2
      },
      {
        "prize": 30000,
        "remaining": 0,
        "total": 4
      },
      {
        "prize": 20000,
        "remaining": 3,
        "total": 7
      },
      {
        "prize": 10000,
        "remaining": 7,
        "total": 12
      },
      {
        "prize": 5000,
        "remaining": 5,
        "total": 13
      },
      {
        "prize": 1000,
        "remaining": 202,
        "total": 520
      },
      {
        "prize": 500,
        "remaining": 442,
        "total": 1120
      },
      {
        "prize": 200,
        "remaining": 1014,
        "total": 2620
      },
      {
        "prize": 100,
        "remaining": 26644,
        "total": 67728
      },
      {
        "prize": 50,
        "remaining": 26690,
        "total": 67652
      },
      {
        "prize": 40,
        "remaining": 61754,
        "total": 156126
      },
      {
        "prize": 20,
        "remaining": 93802,
        "total": 234233
      }
    ],
    "imageUrl": "https://www.molottery.com/media/scratchers/tile/525.png"
  },
  {
    "name": "Top line",
    "price": 1.0,
    "totalTickets": 0,
    "remainingTickets": 0,
    "gameNumber": "522",
    "tiers": [
      {
        "prize": 7777,
        "remaining": 1,
        "total": 5
      },
      {
        "prize": 1000,
        "remaining": 0,
        "total": 5
      },
      {
        "prize": 777,
        "remaining": 3,
        "total": 28
      },
      {
        "prize": 500,
        "remaining": 7,
        "total": 38
      },
      {
        "prize": 100,
        "remaining": 224,
        "total": 1738
      },
      {
        "prize": 50,
        "remaining": 516,
        "total": 4077
      },
      {
        "prize": 30,
        "remaining": 1339,
        "total": 9625
      },
      {
        "prize": 25,
        "remaining": 3280,
        "total": 23259
      },
      {
        "prize": 10,
        "remaining": 11710,
        "total": 75610
      },
      {
        "prize": 7,
        "remaining": 7488,
        "total": 46518
      },
      {
        "prize": 5,
        "remaining": 15642,
        "total": 93036
      },
      {
        "prize": 4,
        "remaining": 8240,
        "total": 46485
      },
      {
        "prize": 3,
        "remaining": 8540,
        "total": 46493
      },
      {
        "prize": 2,
        "remaining": 62581,
        "total": 325629
      },
      {
        "prize": 1,
        "remaining": 167698,
        "total": 802454
      }
    ],
    "imageUrl": "https://www.molottery.com/media/scratchers/tile/522.png"
  },
  {
    "name": "Top line",
    "price": 20.0,
    "totalTickets": 0,
    "remainingTickets": 0,
    "gameNumber": "523",
    "tiers": [
      {
        "prize": 2000000,
        "remaining": 1,
        "total": 2
      },
      {
        "prize": 100000,
        "remaining": 1,
        "total": 4
      },
      {
        "prize": 20000,
        "remaining": 2,
        "total": 5
      },
      {
        "prize": 10000,
        "remaining": 4,
        "total": 11
      },
      {
        "prize": 5000,
        "remaining": 11,
        "total": 25
      },
      {
        "prize": 1000,
        "remaining": 440,
        "total": 1091
      },
      {
        "prize": 500,
        "remaining": 684,
        "total": 1791
      },
      {
        "prize": 200,
        "remaining": 2129,
        "total": 5454
      },
      {
        "prize": 100,
        "remaining": 52621,
        "total": 136397
      },
      {
        "prize": 50,
        "remaining": 54299,
        "total": 140423
      },
      {
        "prize": 40,
        "remaining": 127137,
        "total": 327276
      },
      {
        "prize": 20,
        "remaining": 181970,
        "total": 463574
      }
    ],
    "imageUrl": "https://www.molottery.com/media/scratchers/tile/523.png"
  },
  {
    "name": "Top line",
    "price": 5.0,
    "totalTickets": 0,
    "remainingTickets": 0,
    "gameNumber": "520",
    "tiers": [
      {
        "prize": 100000,
        "remaining": 0,
        "total": 4
      },
      {
        "prize": 20000,
        "remaining": 1,
        "total": 3
      },
      {
        "prize": 5000,
        "remaining": 0,
        "total": 2
      },
      {
        "prize": 1000,
        "remaining": 3,
        "total": 10
      },
      {
        "prize": 500,
        "remaining": 28,
        "total": 148
      },
      {
        "prize": 200,
        "remaining": 58,
        "total": 301
      },
      {
        "prize": 100,
        "remaining": 1925,
        "total": 9897
      },
      {
        "prize": 75,
        "remaining": 2431,
        "total": 12797
      },
      {
        "prize": 50,
        "remaining": 5116,
        "total": 26519
      },
      {
        "prize": 25,
        "remaining": 8992,
        "total": 44960
      },
      {
        "prize": 15,
        "remaining": 24504,
        "total": 119943
      },
      {
        "prize": 10,
        "remaining": 69380,
        "total": 329723
      },
      {
        "prize": 5,
        "remaining": 98387,
        "total": 434637
      }
    ],
    "imageUrl": "https://www.molottery.com/media/scratchers/tile/520.png"
  },
  {
    "name": "Top line",
    "price": 2.0,
    "totalTickets": 0,
    "remainingTickets": 0,
    "gameNumber": "521",
    "tiers": [
      {
        "prize": 25000,
        "remaining": 1,
        "total": 5
      },
      {
        "prize": 5000,
        "remaining": 1,
        "total": 6
      },
      {
        "prize": 1000,
        "remaining": 7,
        "total": 91
      },
      {
        "prize": 500,
        "remaining": 116,
        "total": 887
      },
      {
        "prize": 100,
        "remaining": 994,
        "total": 7112
      },
      {
        "prize": 50,
        "remaining": 2386,
        "total": 14448
      },
      {
        "prize": 20,
        "remaining": 5860,
        "total": 35499
      },
      {
        "prize": 10,
        "remaining": 19071,
        "total": 106497
      },
      {
        "prize": 5,
        "remaining": 17397,
        "total": 106497
      },
      {
        "prize": 4,
        "remaining": 63037,
        "total": 390445
      },
      {
        "prize": 2,
        "remaining": 99213,
        "total": 532573
      }
    ],
    "imageUrl": "https://www.molottery.com/media/scratchers/tile/521.png"
  },
  {
    "name": "Top line",
    "price": 5.0,
    "totalTickets": 0,
    "remainingTickets": 0,
    "gameNumber": "517",
    "tiers": [
      {
        "prize": 100000,
        "remaining": 1,
        "total": 4
      },
      {
        "prize": 20000,
        "remaining": 1,
        "total": 4
      },
      {
        "prize": 5000,
        "remaining": 2,
        "total": 18
      },
      {
        "prize": 1000,
        "remaining": 12,
        "total": 80
      },
      {
        "prize": 500,
        "remaining": 40,
        "total": 286
      },
      {
        "prize": 100,
        "remaining": 1967,
        "total": 13830
      },
      {
        "prize": 50,
        "remaining": 9596,
        "total": 66092
      },
      {
        "prize": 25,
        "remaining": 5743,
        "total": 37606
      },
      {
        "prize": 15,
        "remaining": 22861,
        "total": 142988
      },
      {
        "prize": 10,
        "remaining": 59312,
        "total": 357463
      },
      {
        "prize": 5,
        "remaining": 95947,
        "total": 500472
      }
    ],
    "imageUrl": "https://www.molottery.com/media/scratchers/tile/517.png"
  },
  {
    "name": "Top line",
    "price": 10.0,
    "totalTickets": 0,
    "remainingTickets": 0,
    "gameNumber": "511",
    "tiers": [
      {
        "prize": 1000000,
        "remaining": 0,
        "total": 2
      },
      {
        "prize": 50000,
        "remaining": 1,
        "total": 5
      },
      {
        "prize": 5000,
        "remaining": 14,
        "total": 50
      },
      {
        "prize": 1000,
        "remaining": 231,
        "total": 771
      },
      {
        "prize": 500,
        "remaining": 487,
        "total": 1625
      },
      {
        "prize": 200,
        "remaining": 1384,
        "total": 4651
      },
      {
        "prize": 100,
        "remaining": 11621,
        "total": 38904
      },
      {
        "prize": 50,
        "remaining": 46176,
        "total": 154986
      },
      {
        "prize": 30,
        "remaining": 14001,
        "total": 46381
      },
      {
        "prize": 25,
        "remaining": 15240,
        "total": 50496
      },
      {
        "prize": 20,
        "remaining": 94028,
        "total": 309972
      },
      {
        "prize": 15,
        "remaining": 71794,
        "total": 232479
      },
      {
        "prize": 10,
        "remaining": 193464,
        "total": 619944
      }
    ],
    "imageUrl": "https://www.molottery.com/media/scratchers/tile/511.png"
  },
  {
    "name": "Top line",
    "price": 5.0,
    "totalTickets": 0,
    "remainingTickets": 0,
    "gameNumber": "509",
    "tiers": [
      {
        "prize": 100000,
        "remaining": 0,
        "total": 6
      },
      {
        "prize": 20000,
        "remaining": 3,
        "total": 10
      },
      {
        "prize": 5000,
        "remaining": 2,
        "total": 30
      },
      {
        "prize": 1000,
        "remaining": 43,
        "total": 682
      },
      {
        "prize": 500,
        "remaining": 15,
        "total": 204
      },
      {
        "prize": 200,
        "remaining": 40,
        "total": 803
      },
      {
        "prize": 100,
        "remaining": 709,
        "total": 15354
      },
      {
        "prize": 75,
        "remaining": 171,
        "total": 3184
      },
      {
        "prize": 50,
        "remaining": 579,
        "total": 11849
      },
      {
        "prize": 40,
        "remaining": 1954,
        "total": 39826
      },
      {
        "prize": 25,
        "remaining": 1017,
        "total": 19498
      },
      {
        "prize": 20,
        "remaining": 3752,
        "total": 59687
      },
      {
        "prize": 15,
        "remaining": 14415,
        "total": 238514
      },
      {
        "prize": 10,
        "remaining": 16193,
        "total": 238578
      },
      {
        "prize": 5,
        "remaining": 58760,
        "total": 556704
      }
    ],
    "imageUrl": "https://www.molottery.com/media/scratchers/tile/509.png"
  },
  {
    "name": "Top line",
    "price": 1.0,
    "totalTickets": 0,
    "remainingTickets": 0,
    "gameNumber": "518",
    "tiers": [
      {
        "prize": 2500,
        "remaining": 2,
        "total": 7
      },
      {
        "prize": 1000,
        "remaining": 2,
        "total": 10
      },
      {
        "prize": 500,
        "remaining": 2,
        "total": 15
      },
      {
        "prize": 100,
        "remaining": 364,
        "total": 2015
      },
      {
        "prize": 50,
        "remaining": 4854,
        "total": 27157
      },
      {
        "prize": 15,
        "remaining": 4661,
        "total": 24681
      },
      {
        "prize": 10,
        "remaining": 8259,
        "total": 43167
      },
      {
        "prize": 5,
        "remaining": 9843,
        "total": 49382
      },
      {
        "prize": 4,
        "remaining": 35066,
        "total": 172826
      },
      {
        "prize": 2,
        "remaining": 79758,
        "total": 370156
      },
      {
        "prize": 1,
        "remaining": 205885,
        "total": 851524
      }
    ],
    "imageUrl": "https://www.molottery.com/media/scratchers/tile/518.png"
  },
  {
    "name": "Top line",
    "price": 20.0,
    "totalTickets": 0,
    "remainingTickets": 0,
    "gameNumber": "532",
    "tiers": [
      {
        "prize": 2000000,
        "remaining": 1,
        "total": 2
      },
      {
        "prize": 100000,
        "remaining": 2,
        "total": 4
      },
      {
        "prize": 20000,
        "remaining": 2,
        "total": 5
      },
      {
        "prize": 10000,
        "remaining": 4,
        "total": 11
      },
      {
        "prize": 5000,
        "remaining": 12,
        "total": 25
      },
      {
        "prize": 1000,
        "remaining": 493,
        "total": 1085
      },
      {
        "prize": 500,
        "remaining": 784,
        "total": 1772
      },
      {
        "prize": 200,
        "remaining": 2360,
        "total": 5367
      },
      {
        "prize": 100,
        "remaining": 89271,
        "total": 204058
      },
      {
        "prize": 40,
        "remaining": 130511,
        "total": 296147
      },
      {
        "prize": 20,
        "remaining": 227784,
        "total": 511455
      }
    ],
    "imageUrl": "https://www.molottery.com/media/scratchers/tile/532.png"
  },
  {
    "name": "Top line",
    "price": 20.0,
    "totalTickets": 0,
    "remainingTickets": 0,
    "gameNumber": "519",
    "tiers": [
      {
        "prize": 200,
        "remaining": 16460,
        "total": 52343
      },
      {
        "prize": 100,
        "remaining": 73529,
        "total": 231869
      }
    ],
    "imageUrl": "https://www.molottery.com/media/scratchers/tile/519.png"
  },
  {
    "name": "Top line",
    "price": 50.0,
    "totalTickets": 0,
    "remainingTickets": 0,
    "gameNumber": "508",
    "tiers": [
      {
        "prize": 5000000,
        "remaining": 2,
        "total": 3
      },
      {
        "prize": 1000000,
        "remaining": 2,
        "total": 3
      },
      {
        "prize": 50000,
        "remaining": 33,
        "total": 50
      },
      {
        "prize": 10000,
        "remaining": 177,
        "total": 260
      },
      {
        "prize": 5000,
        "remaining": 482,
        "total": 728
      },
      {
        "prize": 1000,
        "remaining": 1843,
        "total": 2725
      },
      {
        "prize": 500,
        "remaining": 93174,
        "total": 140568
      },
      {
        "prize": 200,
        "remaining": 103091,
        "total": 155521
      },
      {
        "prize": 100,
        "remaining": 632705,
        "total": 954743
      },
      {
        "prize": 50,
        "remaining": 544078,
        "total": 818404
      }
    ],
    "imageUrl": "https://www.molottery.com/media/scratchers/tile/508.png"
  },
  {
    "name": "Top line",
    "price": 2.0,
    "totalTickets": 0,
    "remainingTickets": 0,
    "gameNumber": "515",
    "tiers": [
      {
        "prize": 33333,
        "remaining": 2,
        "total": 5
      },
      {
        "prize": 3333,
        "remaining": 0,
        "total": 5
      },
      {
        "prize": 1000,
        "remaining": 12,
        "total": 46
      },
      {
        "prize": 333,
        "remaining": 125,
        "total": 448
      },
      {
        "prize": 100,
        "remaining": 2003,
        "total": 7432
      },
      {
        "prize": 30,
        "remaining": 12819,
        "total": 46903
      },
      {
        "prize": 20,
        "remaining": 7384,
        "total": 26492
      },
      {
        "prize": 15,
        "remaining": 9781,
        "total": 35342
      },
      {
        "prize": 10,
        "remaining": 15032,
        "total": 53044
      },
      {
        "prize": 5,
        "remaining": 30807,
        "total": 106022
      },
      {
        "prize": 4,
        "remaining": 84800,
        "total": 282736
      },
      {
        "prize": 2,
        "remaining": 196165,
        "total": 636156
      }
    ],
    "imageUrl": "https://www.molottery.com/media/scratchers/tile/515.png"
  },
  {
    "name": "Top line",
    "price": 20.0,
    "totalTickets": 0,
    "remainingTickets": 0,
    "gameNumber": "516",
    "tiers": [
      {
        "prize": 2000000,
        "remaining": 1,
        "total": 2
      },
      {
        "prize": 100000,
        "remaining": 3,
        "total": 4
      },
      {
        "prize": 20000,
        "remaining": 2,
        "total": 5
      },
      {
        "prize": 10000,
        "remaining": 5,
        "total": 11
      },
      {
        "prize": 5000,
        "remaining": 14,
        "total": 25
      },
      {
        "prize": 1000,
        "remaining": 584,
        "total": 1108
      },
      {
        "prize": 500,
        "remaining": 939,
        "total": 1808
      },
      {
        "prize": 200,
        "remaining": 2832,
        "total": 5467
      },
      {
        "prize": 100,
        "remaining": 70553,
        "total": 136190
      },
      {
        "prize": 50,
        "remaining": 72634,
        "total": 140277
      },
      {
        "prize": 40,
        "remaining": 169648,
        "total": 326655
      },
      {
        "prize": 20,
        "remaining": 241844,
        "total": 462687
      }
    ],
    "imageUrl": "https://www.molottery.com/media/scratchers/tile/516.png"
  },
  {
    "name": "Top line",
    "price": 5.0,
    "totalTickets": 0,
    "remainingTickets": 0,
    "gameNumber": "512",
    "tiers": [
      {
        "prize": 100000,
        "remaining": 1,
        "total": 6
      },
      {
        "prize": 20000,
        "remaining": 1,
        "total": 6
      },
      {
        "prize": 5000,
        "remaining": 0,
        "total": 29
      },
      {
        "prize": 1000,
        "remaining": 43,
        "total": 720
      },
      {
        "prize": 500,
        "remaining": 12,
        "total": 185
      },
      {
        "prize": 200,
        "remaining": 64,
        "total": 874
      },
      {
        "prize": 100,
        "remaining": 1229,
        "total": 19851
      },
      {
        "prize": 75,
        "remaining": 174,
        "total": 3584
      },
      {
        "prize": 50,
        "remaining": 1093,
        "total": 13388
      },
      {
        "prize": 40,
        "remaining": 2927,
        "total": 44688
      },
      {
        "prize": 25,
        "remaining": 3219,
        "total": 32390
      },
      {
        "prize": 20,
        "remaining": 4543,
        "total": 66819
      },
      {
        "prize": 15,
        "remaining": 17257,
        "total": 267416
      },
      {
        "prize": 10,
        "remaining": 20266,
        "total": 267380
      },
      {
        "prize": 5,
        "remaining": 67709,
        "total": 623816
      }
    ],
    "imageUrl": "https://www.molottery.com/media/scratchers/tile/512.png"
  },
  {
    "name": "Top line",
    "price": 1.0,
    "totalTickets": 0,
    "remainingTickets": 0,
    "gameNumber": "513",
    "tiers": [
      {
        "prize": 7000,
        "remaining": 2,
        "total": 5
      },
      {
        "prize": 3000,
        "remaining": 1,
        "total": 5
      },
      {
        "prize": 2000,
        "remaining": 1,
        "total": 5
      },
      {
        "prize": 1000,
        "remaining": 2,
        "total": 5
      },
      {
        "prize": 500,
        "remaining": 10,
        "total": 46
      },
      {
        "prize": 100,
        "remaining": 627,
        "total": 1788
      },
      {
        "prize": 50,
        "remaining": 1425,
        "total": 4185
      },
      {
        "prize": 30,
        "remaining": 3381,
        "total": 9880
      },
      {
        "prize": 25,
        "remaining": 8191,
        "total": 23885
      },
      {
        "prize": 10,
        "remaining": 20846,
        "total": 59740
      },
      {
        "prize": 9,
        "remaining": 16990,
        "total": 47770
      },
      {
        "prize": 6,
        "remaining": 4258,
        "total": 11970
      },
      {
        "prize": 5,
        "remaining": 34246,
        "total": 95481
      },
      {
        "prize": 4,
        "remaining": 17389,
        "total": 47774
      },
      {
        "prize": 3,
        "remaining": 17567,
        "total": 47711
      },
      {
        "prize": 2,
        "remaining": 124991,
        "total": 334343
      },
      {
        "prize": 1,
        "remaining": 320544,
        "total": 836085
      }
    ],
    "imageUrl": "https://www.molottery.com/media/scratchers/tile/513.png"
  },
  {
    "name": "Top line",
    "price": 10.0,
    "totalTickets": 0,
    "remainingTickets": 0,
    "gameNumber": "503",
    "tiers": [
      {
        "prize": 1000000,
        "remaining": 1,
        "total": 2
      },
      {
        "prize": 50000,
        "remaining": 0,
        "total": 5
      },
      {
        "prize": 5000,
        "remaining": 3,
        "total": 50
      },
      {
        "prize": 1000,
        "remaining": 40,
        "total": 762
      },
      {
        "prize": 500,
        "remaining": 47,
        "total": 1573
      },
      {
        "prize": 200,
        "remaining": 151,
        "total": 4457
      },
      {
        "prize": 100,
        "remaining": 2607,
        "total": 74212
      },
      {
        "prize": 50,
        "remaining": 2698,
        "total": 74212
      },
      {
        "prize": 30,
        "remaining": 1626,
        "total": 44624
      },
      {
        "prize": 25,
        "remaining": 1838,
        "total": 48234
      },
      {
        "prize": 20,
        "remaining": 12174,
        "total": 296770
      },
      {
        "prize": 15,
        "remaining": 11539,
        "total": 222636
      },
      {
        "prize": 10,
        "remaining": 31555,
        "total": 593852
      }
    ],
    "imageUrl": "https://www.molottery.com/media/scratchers/tile/503.png"
  },
  {
    "name": "Top line",
    "price": 5.0,
    "totalTickets": 0,
    "remainingTickets": 0,
    "gameNumber": "506",
    "tiers": [
      {
        "prize": 100000,
        "remaining": 1,
        "total": 5
      },
      {
        "prize": 20000,
        "remaining": 1,
        "total": 9
      },
      {
        "prize": 5000,
        "remaining": 3,
        "total": 26
      },
      {
        "prize": 1000,
        "remaining": 15,
        "total": 153
      },
      {
        "prize": 500,
        "remaining": 13,
        "total": 180
      },
      {
        "prize": 200,
        "remaining": 51,
        "total": 698
      },
      {
        "prize": 100,
        "remaining": 1194,
        "total": 13339
      },
      {
        "prize": 75,
        "remaining": 182,
        "total": 2764
      },
      {
        "prize": 50,
        "remaining": 1067,
        "total": 10425
      },
      {
        "prize": 40,
        "remaining": 2190,
        "total": 34645
      },
      {
        "prize": 25,
        "remaining": 3365,
        "total": 34500
      },
      {
        "prize": 20,
        "remaining": 8905,
        "total": 103772
      },
      {
        "prize": 10,
        "remaining": 62933,
        "total": 656714
      }
    ],
    "imageUrl": "https://www.molottery.com/media/scratchers/tile/506.png"
  },
  {
    "name": "Top line",
    "price": 2.0,
    "totalTickets": 0,
    "remainingTickets": 0,
    "gameNumber": "510",
    "tiers": [
      {
        "prize": 25000,
        "remaining": 0,
        "total": 5
      },
      {
        "prize": 5000,
        "remaining": 3,
        "total": 8
      },
      {
        "prize": 1000,
        "remaining": 15,
        "total": 88
      },
      {
        "prize": 500,
        "remaining": 144,
        "total": 879
      },
      {
        "prize": 100,
        "remaining": 1215,
        "total": 6946
      },
      {
        "prize": 50,
        "remaining": 2457,
        "total": 14139
      },
      {
        "prize": 20,
        "remaining": 6182,
        "total": 34677
      },
      {
        "prize": 10,
        "remaining": 19275,
        "total": 104031
      },
      {
        "prize": 5,
        "remaining": 20295,
        "total": 104031
      },
      {
        "prize": 4,
        "remaining": 77532,
        "total": 381373
      },
      {
        "prize": 2,
        "remaining": 110691,
        "total": 520303
      }
    ],
    "imageUrl": "https://www.molottery.com/media/scratchers/tile/510.png"
  },
  {
    "name": "Top line",
    "price": 20.0,
    "totalTickets": 0,
    "remainingTickets": 0,
    "gameNumber": "488",
    "tiers": [
      {
        "prize": 2000000,
        "remaining": 1,
        "total": 2
      },
      {
        "prize": 100000,
        "remaining": 2,
        "total": 4
      },
      {
        "prize": 20000,
        "remaining": 2,
        "total": 5
      },
      {
        "prize": 10000,
        "remaining": 8,
        "total": 11
      },
      {
        "prize": 5000,
        "remaining": 16,
        "total": 25
      },
      {
        "prize": 1000,
        "remaining": 602,
        "total": 1103
      },
      {
        "prize": 500,
        "remaining": 2417,
        "total": 4510
      },
      {
        "prize": 200,
        "remaining": 4024,
        "total": 7501
      },
      {
        "prize": 100,
        "remaining": 63123,
        "total": 118319
      },
      {
        "prize": 50,
        "remaining": 74702,
        "total": 140196
      },
      {
        "prize": 40,
        "remaining": 175279,
        "total": 326434
      },
      {
        "prize": 20,
        "remaining": 250090,
        "total": 462250
      }
    ],
    "imageUrl": "https://www.molottery.com/media/scratchers/tile/488.png"
  },
  {
    "name": "Top line",
    "price": 3.0,
    "totalTickets": 0,
    "remainingTickets": 0,
    "gameNumber": "497",
    "tiers": [
      {
        "prize": 55558,
        "remaining": 0,
        "total": 6
      },
      {
        "prize": 25003,
        "remaining": 0,
        "total": 3
      },
      {
        "prize": 10003,
        "remaining": 1,
        "total": 3
      },
      {
        "prize": 3003,
        "remaining": 2,
        "total": 12
      },
      {
        "prize": 1009,
        "remaining": 5,
        "total": 23
      },
      {
        "prize": 1003,
        "remaining": 14,
        "total": 45
      },
      {
        "prize": 503,
        "remaining": 9,
        "total": 48
      },
      {
        "prize": 500,
        "remaining": 28,
        "total": 142
      },
      {
        "prize": 450,
        "remaining": 30,
        "total": 145
      },
      {
        "prize": 300,
        "remaining": 24,
        "total": 141
      },
      {
        "prize": 206,
        "remaining": 18,
        "total": 94
      },
      {
        "prize": 200,
        "remaining": 66,
        "total": 376
      },
      {
        "prize": 150,
        "remaining": 168,
        "total": 945
      },
      {
        "prize": 103,
        "remaining": 360,
        "total": 1877
      },
      {
        "prize": 100,
        "remaining": 974,
        "total": 5010
      },
      {
        "prize": 53,
        "remaining": 1016,
        "total": 5195
      },
      {
        "prize": 40,
        "remaining": 2001,
        "total": 9881
      },
      {
        "prize": 33,
        "remaining": 426,
        "total": 2356
      },
      {
        "prize": 30,
        "remaining": 560,
        "total": 2367
      },
      {
        "prize": 20,
        "remaining": 11234,
        "total": 56544
      },
      {
        "prize": 16,
        "remaining": 11672,
        "total": 56544
      },
      {
        "prize": 10,
        "remaining": 41691,
        "total": 169632
      },
      {
        "prize": 6,
        "remaining": 142473,
        "total": 565485
      },
      {
        "prize": 3,
        "remaining": 144053,
        "total": 565350
      }
    ],
    "imageUrl": "https://www.molottery.com/media/scratchers/tile/497.png"
  },
  {
    "name": "Top line",
    "price": 10.0,
    "totalTickets": 0,
    "remainingTickets": 0,
    "gameNumber": "505",
    "tiers": [
      {
        "prize": 777777,
        "remaining": 0,
        "total": 2
      },
      {
        "prize": 77777,
        "remaining": 1,
        "total": 5
      },
      {
        "prize": 7777,
        "remaining": 3,
        "total": 16
      },
      {
        "prize": 777,
        "remaining": 56,
        "total": 231
      },
      {
        "prize": 577,
        "remaining": 73,
        "total": 307
      },
      {
        "prize": 277,
        "remaining": 506,
        "total": 2271
      },
      {
        "prize": 177,
        "remaining": 1330,
        "total": 6127
      },
      {
        "prize": 77,
        "remaining": 33001,
        "total": 152000
      },
      {
        "prize": 27,
        "remaining": 25851,
        "total": 114029
      },
      {
        "prize": 17,
        "remaining": 121487,
        "total": 532000
      },
      {
        "prize": 10,
        "remaining": 144914,
        "total": 608000
      }
    ],
    "imageUrl": "https://www.molottery.com/media/scratchers/tile/505.png"
  },
  {
    "name": "Top line",
    "price": 5.0,
    "totalTickets": 0,
    "remainingTickets": 0,
    "gameNumber": "492",
    "tiers": [
      {
        "prize": 100000,
        "remaining": 2,
        "total": 5
      },
      {
        "prize": 20000,
        "remaining": 0,
        "total": 3
      },
      {
        "prize": 2000,
        "remaining": 2,
        "total": 8
      },
      {
        "prize": 1000,
        "remaining": 4,
        "total": 20
      },
      {
        "prize": 200,
        "remaining": 919,
        "total": 8683
      },
      {
        "prize": 100,
        "remaining": 1456,
        "total": 13918
      },
      {
        "prize": 40,
        "remaining": 3979,
        "total": 36390
      },
      {
        "prize": 20,
        "remaining": 8269,
        "total": 69307
      },
      {
        "prize": 15,
        "remaining": 24589,
        "total": 207921
      },
      {
        "prize": 10,
        "remaining": 26109,
        "total": 207941
      },
      {
        "prize": 5,
        "remaining": 78404,
        "total": 485109
      }
    ],
    "imageUrl": "https://www.molottery.com/media/scratchers/tile/492.png"
  },
  {
    "name": "Top line",
    "price": 5.0,
    "totalTickets": 0,
    "remainingTickets": 0,
    "gameNumber": "504",
    "tiers": [
      {
        "prize": 100000,
        "remaining": 0,
        "total": 6
      },
      {
        "prize": 30000,
        "remaining": 0,
        "total": 3
      },
      {
        "prize": 20000,
        "remaining": 1,
        "total": 3
      },
      {
        "prize": 15000,
        "remaining": 0,
        "total": 6
      },
      {
        "prize": 10000,
        "remaining": 1,
        "total": 7
      },
      {
        "prize": 5000,
        "remaining": 0,
        "total": 14
      },
      {
        "prize": 1500,
        "remaining": 3,
        "total": 32
      },
      {
        "prize": 1000,
        "remaining": 5,
        "total": 125
      },
      {
        "prize": 500,
        "remaining": 13,
        "total": 248
      },
      {
        "prize": 200,
        "remaining": 11,
        "total": 424
      },
      {
        "prize": 100,
        "remaining": 444,
        "total": 11978
      },
      {
        "prize": 75,
        "remaining": 250,
        "total": 6724
      },
      {
        "prize": 50,
        "remaining": 1080,
        "total": 26454
      },
      {
        "prize": 30,
        "remaining": 366,
        "total": 6939
      },
      {
        "prize": 25,
        "remaining": 1888,
        "total": 41874
      },
      {
        "prize": 20,
        "remaining": 4999,
        "total": 104808
      },
      {
        "prize": 15,
        "remaining": 18193,
        "total": 251406
      },
      {
        "prize": 10,
        "remaining": 19960,
        "total": 251376
      },
      {
        "prize": 5,
        "remaining": 57151,
        "total": 628488
      }
    ],
    "imageUrl": "https://www.molottery.com/media/scratchers/tile/504.png"
  },
  {
    "name": "Top line",
    "price": 5.0,
    "totalTickets": 0,
    "remainingTickets": 0,
    "gameNumber": "500",
    "tiers": [
      {
        "prize": 77777,
        "remaining": 0,
        "total": 5
      },
      {
        "prize": 10000,
        "remaining": 0,
        "total": 4
      },
      {
        "prize": 7777,
        "remaining": 0,
        "total": 12
      },
      {
        "prize": 1000,
        "remaining": 1,
        "total": 17
      },
      {
        "prize": 777,
        "remaining": 14,
        "total": 230
      },
      {
        "prize": 500,
        "remaining": 10,
        "total": 168
      },
      {
        "prize": 277,
        "remaining": 12,
        "total": 280
      },
      {
        "prize": 77,
        "remaining": 2457,
        "total": 43299
      },
      {
        "prize": 27,
        "remaining": 4944,
        "total": 80919
      },
      {
        "prize": 17,
        "remaining": 4291,
        "total": 68878
      },
      {
        "prize": 15,
        "remaining": 8749,
        "total": 137756
      },
      {
        "prize": 10,
        "remaining": 14217,
        "total": 206618
      },
      {
        "prize": 5,
        "remaining": 37284,
        "total": 482178
      }
    ],
    "imageUrl": "https://www.molottery.com/media/scratchers/tile/500.png"
  },
  {
    "name": "Top line",
    "price": 2.0,
    "totalTickets": 0,
    "remainingTickets": 0,
    "gameNumber": "501",
    "tiers": [
      {
        "prize": 20000,
        "remaining": 1,
        "total": 6
      },
      {
        "prize": 2500,
        "remaining": 7,
        "total": 22
      },
      {
        "prize": 1000,
        "remaining": 23,
        "total": 66
      },
      {
        "prize": 500,
        "remaining": 77,
        "total": 264
      },
      {
        "prize": 100,
        "remaining": 1920,
        "total": 7129
      },
      {
        "prize": 40,
        "remaining": 9315,
        "total": 35707
      },
      {
        "prize": 20,
        "remaining": 7174,
        "total": 26767
      },
      {
        "prize": 15,
        "remaining": 9625,
        "total": 35707
      },
      {
        "prize": 10,
        "remaining": 15336,
        "total": 53548
      },
      {
        "prize": 5,
        "remaining": 32666,
        "total": 107199
      },
      {
        "prize": 4,
        "remaining": 84158,
        "total": 285667
      },
      {
        "prize": 2,
        "remaining": 212228,
        "total": 642704
      }
    ],
    "imageUrl": "https://www.molottery.com/media/scratchers/tile/501.png"
  },
  {
    "name": "Top line",
    "price": 20.0,
    "totalTickets": 0,
    "remainingTickets": 0,
    "gameNumber": "502",
    "tiers": [
      {
        "prize": 2000000,
        "remaining": 1,
        "total": 2
      },
      {
        "prize": 100000,
        "remaining": 3,
        "total": 4
      },
      {
        "prize": 20000,
        "remaining": 2,
        "total": 5
      },
      {
        "prize": 10000,
        "remaining": 7,
        "total": 11
      },
      {
        "prize": 5000,
        "remaining": 13,
        "total": 25
      },
      {
        "prize": 1000,
        "remaining": 505,
        "total": 1091
      },
      {
        "prize": 500,
        "remaining": 808,
        "total": 1800
      },
      {
        "prize": 200,
        "remaining": 2487,
        "total": 5483
      },
      {
        "prize": 100,
        "remaining": 61939,
        "total": 136439
      },
      {
        "prize": 50,
        "remaining": 63763,
        "total": 140437
      },
      {
        "prize": 40,
        "remaining": 149272,
        "total": 327261
      },
      {
        "prize": 20,
        "remaining": 213053,
        "total": 463632
      }
    ],
    "imageUrl": "https://www.molottery.com/media/scratchers/tile/502.png"
  },
  {
    "name": "Top line",
    "price": 5.0,
    "totalTickets": 0,
    "remainingTickets": 0,
    "gameNumber": "495",
    "tiers": [
      {
        "prize": 100000,
        "remaining": 1,
        "total": 4
      },
      {
        "prize": 25000,
        "remaining": 1,
        "total": 3
      },
      {
        "prize": 2500,
        "remaining": 7,
        "total": 18
      },
      {
        "prize": 500,
        "remaining": 83,
        "total": 296
      },
      {
        "prize": 100,
        "remaining": 3439,
        "total": 12256
      },
      {
        "prize": 50,
        "remaining": 14100,
        "total": 49612
      },
      {
        "prize": 25,
        "remaining": 42353,
        "total": 146886
      },
      {
        "prize": 15,
        "remaining": 42768,
        "total": 146886
      },
      {
        "prize": 10,
        "remaining": 64662,
        "total": 220319
      },
      {
        "prize": 5,
        "remaining": 160718,
        "total": 514121
      }
    ],
    "imageUrl": "https://www.molottery.com/media/scratchers/tile/495.png"
  },
  {
    "name": "Top line",
    "price": 10.0,
    "totalTickets": 0,
    "remainingTickets": 0,
    "gameNumber": "493",
    "tiers": [
      {
        "prize": 1000000,
        "remaining": 1,
        "total": 2
      },
      {
        "prize": 50000,
        "remaining": 1,
        "total": 5
      },
      {
        "prize": 5000,
        "remaining": 13,
        "total": 50
      },
      {
        "prize": 1000,
        "remaining": 197,
        "total": 755
      },
      {
        "prize": 500,
        "remaining": 386,
        "total": 1567
      },
      {
        "prize": 200,
        "remaining": 1139,
        "total": 4517
      },
      {
        "prize": 100,
        "remaining": 9321,
        "total": 37525
      },
      {
        "prize": 50,
        "remaining": 37981,
        "total": 150188
      },
      {
        "prize": 30,
        "remaining": 11417,
        "total": 45083
      },
      {
        "prize": 25,
        "remaining": 12331,
        "total": 48859
      },
      {
        "prize": 20,
        "remaining": 77172,
        "total": 300376
      },
      {
        "prize": 15,
        "remaining": 58639,
        "total": 225282
      },
      {
        "prize": 10,
        "remaining": 158673,
        "total": 600752
      }
    ],
    "imageUrl": "https://www.molottery.com/media/scratchers/tile/493.png"
  },
  {
    "name": "Top line",
    "price": 5.0,
    "totalTickets": 0,
    "remainingTickets": 0,
    "gameNumber": "490",
    "tiers": [
      {
        "prize": 100000,
        "remaining": 1,
        "total": 7
      },
      {
        "prize": 20000,
        "remaining": 2,
        "total": 6
      },
      {
        "prize": 5000,
        "remaining": 2,
        "total": 29
      },
      {
        "prize": 1000,
        "remaining": 131,
        "total": 769
      },
      {
        "prize": 500,
        "remaining": 29,
        "total": 184
      },
      {
        "prize": 200,
        "remaining": 185,
        "total": 972
      },
      {
        "prize": 100,
        "remaining": 3664,
        "total": 21967
      },
      {
        "prize": 75,
        "remaining": 644,
        "total": 3901
      },
      {
        "prize": 50,
        "remaining": 2636,
        "total": 14881
      },
      {
        "prize": 40,
        "remaining": 8580,
        "total": 49318
      },
      {
        "prize": 25,
        "remaining": 6583,
        "total": 35768
      },
      {
        "prize": 20,
        "remaining": 13238,
        "total": 73864
      },
      {
        "prize": 15,
        "remaining": 51025,
        "total": 295562
      },
      {
        "prize": 10,
        "remaining": 53881,
        "total": 295552
      },
      {
        "prize": 5,
        "remaining": 142836,
        "total": 689479
      }
    ],
    "imageUrl": "https://www.molottery.com/media/scratchers/tile/490.png"
  },
  {
    "name": "Top line",
    "price": 30.0,
    "totalTickets": 0,
    "remainingTickets": 0,
    "gameNumber": "494",
    "tiers": [
      {
        "prize": 3000000,
        "remaining": 1,
        "total": 3
      },
      {
        "prize": 100000,
        "remaining": 1,
        "total": 3
      },
      {
        "prize": 10000,
        "remaining": 7,
        "total": 18
      },
      {
        "prize": 5000,
        "remaining": 18,
        "total": 42
      },
      {
        "prize": 1000,
        "remaining": 36,
        "total": 94
      },
      {
        "prize": 500,
        "remaining": 3681,
        "total": 9453
      },
      {
        "prize": 200,
        "remaining": 30062,
        "total": 76919
      },
      {
        "prize": 100,
        "remaining": 88245,
        "total": 226467
      },
      {
        "prize": 60,
        "remaining": 283766,
        "total": 724687
      },
      {
        "prize": 30,
        "remaining": 178793,
        "total": 452934
      }
    ],
    "imageUrl": "https://www.molottery.com/media/scratchers/tile/494.png"
  },
  {
    "name": "Top line",
    "price": 5.0,
    "totalTickets": 0,
    "remainingTickets": 0,
    "gameNumber": "487",
    "tiers": [
      {
        "prize": 100000,
        "remaining": 2,
        "total": 5
      },
      {
        "prize": 25000,
        "remaining": 1,
        "total": 4
      },
      {
        "prize": 2500,
        "remaining": 8,
        "total": 20
      },
      {
        "prize": 500,
        "remaining": 148,
        "total": 334
      },
      {
        "prize": 100,
        "remaining": 6135,
        "total": 13720
      },
      {
        "prize": 50,
        "remaining": 24364,
        "total": 54569
      },
      {
        "prize": 25,
        "remaining": 73742,
        "total": 163670
      },
      {
        "prize": 15,
        "remaining": 74116,
        "total": 163706
      },
      {
        "prize": 10,
        "remaining": 111664,
        "total": 245550
      },
      {
        "prize": 5,
        "remaining": 270905,
        "total": 572908
      }
    ],
    "imageUrl": "https://www.molottery.com/media/scratchers/tile/487.png"
  },
  {
    "name": "Top line",
    "price": 3.0,
    "totalTickets": 0,
    "remainingTickets": 0,
    "gameNumber": "477",
    "tiers": [
      {
        "prize": 50000,
        "remaining": 1,
        "total": 10
      },
      {
        "prize": 5000,
        "remaining": 1,
        "total": 32
      },
      {
        "prize": 520,
        "remaining": 10,
        "total": 336
      },
      {
        "prize": 500,
        "remaining": 19,
        "total": 332
      },
      {
        "prize": 103,
        "remaining": 255,
        "total": 4922
      },
      {
        "prize": 100,
        "remaining": 257,
        "total": 5196
      },
      {
        "prize": 60,
        "remaining": 448,
        "total": 9888
      },
      {
        "prize": 53,
        "remaining": 61,
        "total": 832
      },
      {
        "prize": 50,
        "remaining": 659,
        "total": 10718
      },
      {
        "prize": 20,
        "remaining": 4925,
        "total": 79016
      },
      {
        "prize": 16,
        "remaining": 2290,
        "total": 39562
      },
      {
        "prize": 10,
        "remaining": 22892,
        "total": 315848
      },
      {
        "prize": 6,
        "remaining": 68236,
        "total": 790376
      },
      {
        "prize": 3,
        "remaining": 107526,
        "total": 790160
      }
    ],
    "imageUrl": "https://www.molottery.com/media/scratchers/tile/477.png"
  },
  {
    "name": "Top line",
    "price": 5.0,
    "totalTickets": 0,
    "remainingTickets": 0,
    "gameNumber": "486",
    "tiers": [
      {
        "prize": 100000,
        "remaining": 2,
        "total": 6
      },
      {
        "prize": 20000,
        "remaining": 1,
        "total": 3
      },
      {
        "prize": 5000,
        "remaining": 1,
        "total": 8
      },
      {
        "prize": 500,
        "remaining": 877,
        "total": 4092
      },
      {
        "prize": 100,
        "remaining": 3831,
        "total": 18209
      },
      {
        "prize": 40,
        "remaining": 9479,
        "total": 44189
      },
      {
        "prize": 20,
        "remaining": 18346,
        "total": 83942
      },
      {
        "prize": 15,
        "remaining": 55282,
        "total": 251699
      },
      {
        "prize": 10,
        "remaining": 56130,
        "total": 251953
      },
      {
        "prize": 5,
        "remaining": 144618,
        "total": 587721
      }
    ],
    "imageUrl": "https://www.molottery.com/media/scratchers/tile/486.png"
  },
  {
    "name": "Top line",
    "price": 10.0,
    "totalTickets": 0,
    "remainingTickets": 0,
    "gameNumber": "471",
    "tiers": [
      {
        "prize": 1000000,
        "remaining": 1,
        "total": 2
      },
      {
        "prize": 50000,
        "remaining": 2,
        "total": 5
      },
      {
        "prize": 5000,
        "remaining": 7,
        "total": 50
      },
      {
        "prize": 1000,
        "remaining": 123,
        "total": 745
      },
      {
        "prize": 500,
        "remaining": 203,
        "total": 1560
      },
      {
        "prize": 200,
        "remaining": 589,
        "total": 4472
      },
      {
        "prize": 100,
        "remaining": 9855,
        "total": 74178
      },
      {
        "prize": 50,
        "remaining": 9926,
        "total": 74178
      },
      {
        "prize": 30,
        "remaining": 10001,
        "total": 74178
      },
      {
        "prize": 20,
        "remaining": 62118,
        "total": 445133
      },
      {
        "prize": 10,
        "remaining": 100862,
        "total": 667472
      }
    ],
    "imageUrl": "https://www.molottery.com/media/scratchers/tile/471.png"
  },
  {
    "name": "Top line",
    "price": 10.0,
    "totalTickets": 0,
    "remainingTickets": 0,
    "gameNumber": "474",
    "tiers": [
      {
        "prize": 100,
        "remaining": 17832,
        "total": 144012
      },
      {
        "prize": 50,
        "remaining": 30016,
        "total": 239975
      }
    ],
    "imageUrl": "https://www.molottery.com/media/scratchers/tile/474.png"
  },
  {
    "name": "Top line",
    "price": 50.0,
    "totalTickets": 0,
    "remainingTickets": 0,
    "gameNumber": "464",
    "tiers": [
      {
        "prize": 5000000,
        "remaining": 0,
        "total": 3
      },
      {
        "prize": 1000000,
        "remaining": 2,
        "total": 3
      },
      {
        "prize": 50000,
        "remaining": 16,
        "total": 40
      },
      {
        "prize": 10000,
        "remaining": 107,
        "total": 250
      },
      {
        "prize": 5000,
        "remaining": 296,
        "total": 700
      },
      {
        "prize": 1000,
        "remaining": 1097,
        "total": 2566
      },
      {
        "prize": 500,
        "remaining": 43550,
        "total": 103102
      },
      {
        "prize": 200,
        "remaining": 92580,
        "total": 218830
      },
      {
        "prize": 100,
        "remaining": 218105,
        "total": 514726
      },
      {
        "prize": 75,
        "remaining": 437824,
        "total": 1029452
      }
    ],
    "imageUrl": "https://www.molottery.com/media/scratchers/tile/464.png"
  },
  {
    "name": "Top line",
    "price": 30.0,
    "totalTickets": 0,
    "remainingTickets": 0,
    "gameNumber": "453",
    "tiers": [
      {
        "prize": 3000000,
        "remaining": 1,
        "total": 3
      },
      {
        "prize": 100000,
        "remaining": 1,
        "total": 3
      },
      {
        "prize": 30000,
        "remaining": 1,
        "total": 9
      },
      {
        "prize": 6000,
        "remaining": 14,
        "total": 57
      },
      {
        "prize": 3000,
        "remaining": 15,
        "total": 57
      },
      {
        "prize": 1000,
        "remaining": 23,
        "total": 94
      },
      {
        "prize": 500,
        "remaining": 3662,
        "total": 16055
      },
      {
        "prize": 300,
        "remaining": 1785,
        "total": 7755
      },
      {
        "prize": 200,
        "remaining": 4040,
        "total": 17690
      },
      {
        "prize": 100,
        "remaining": 49982,
        "total": 221153
      },
      {
        "prize": 60,
        "remaining": 60991,
        "total": 265387
      },
      {
        "prize": 50,
        "remaining": 81025,
        "total": 353783
      },
      {
        "prize": 40,
        "remaining": 82567,
        "total": 353818
      },
      {
        "prize": 30,
        "remaining": 105601,
        "total": 442463
      }
    ],
    "imageUrl": "https://www.molottery.com/media/scratchers/tile/453.png"
  },
  {
    "name": "Top line",
    "price": 10.0,
    "totalTickets": 0,
    "remainingTickets": 0,
    "gameNumber": "448",
    "tiers": [
      {
        "prize": 1000000,
        "remaining": 1,
        "total": 2
      },
      {
        "prize": 50000,
        "remaining": 1,
        "total": 5
      },
      {
        "prize": 5000,
        "remaining": 11,
        "total": 50
      },
      {
        "prize": 1000,
        "remaining": 184,
        "total": 739
      },
      {
        "prize": 500,
        "remaining": 404,
        "total": 1575
      },
      {
        "prize": 200,
        "remaining": 1139,
        "total": 4532
      },
      {
        "prize": 100,
        "remaining": 9616,
        "total": 37682
      },
      {
        "prize": 50,
        "remaining": 38809,
        "total": 150526
      },
      {
        "prize": 30,
        "remaining": 11648,
        "total": 45123
      },
      {
        "prize": 25,
        "remaining": 12682,
        "total": 48981
      },
      {
        "prize": 20,
        "remaining": 78595,
        "total": 301052
      },
      {
        "prize": 15,
        "remaining": 59713,
        "total": 225789
      },
      {
        "prize": 10,
        "remaining": 161762,
        "total": 602104
      }
    ],
    "imageUrl": "https://www.molottery.com/media/scratchers/tile/448.png"
  },
  {
    "name": "Top line",
    "price": 50.0,
    "totalTickets": 0,
    "remainingTickets": 0,
    "gameNumber": "421",
    "tiers": [
      {
        "prize": 5000000,
        "remaining": 0,
        "total": 3
      },
      {
        "prize": 1000000,
        "remaining": 0,
        "total": 6
      },
      {
        "prize": 50000,
        "remaining": 5,
        "total": 50
      },
      {
        "prize": 10000,
        "remaining": 39,
        "total": 250
      },
      {
        "prize": 5000,
        "remaining": 122,
        "total": 700
      },
      {
        "prize": 1000,
        "remaining": 429,
        "total": 2622
      },
      {
        "prize": 500,
        "remaining": 20507,
        "total": 128761
      },
      {
        "prize": 200,
        "remaining": 8417,
        "total": 52409
      },
      {
        "prize": 100,
        "remaining": 147426,
        "total": 917236
      },
      {
        "prize": 60,
        "remaining": 108347,
        "total": 654962
      },
      {
        "prize": 50,
        "remaining": 65504,
        "total": 392929
      }
    ],
    "imageUrl": "https://www.molottery.com/media/scratchers/tile/421.png"
  },
  {
    "name": "Top line",
    "price": 10.0,
    "totalTickets": 0,
    "remainingTickets": 0,
    "gameNumber": "405",
    "tiers": [
      {
        "prize": 1000000,
        "remaining": 1,
        "total": 2
      },
      {
        "prize": 50000,
        "remaining": 0,
        "total": 5
      },
      {
        "prize": 5000,
        "remaining": 6,
        "total": 50
      },
      {
        "prize": 1000,
        "remaining": 102,
        "total": 741
      },
      {
        "prize": 500,
        "remaining": 202,
        "total": 1568
      },
      {
        "prize": 200,
        "remaining": 633,
        "total": 4497
      },
      {
        "prize": 100,
        "remaining": 10473,
        "total": 74651
      },
      {
        "prize": 50,
        "remaining": 10585,
        "total": 74651
      },
      {
        "prize": 30,
        "remaining": 6417,
        "total": 44818
      },
      {
        "prize": 25,
        "remaining": 7056,
        "total": 48511
      },
      {
        "prize": 20,
        "remaining": 44174,
        "total": 298646
      },
      {
        "prize": 15,
        "remaining": 35011,
        "total": 223953
      },
      {
        "prize": 10,
        "remaining": 94650,
        "total": 597124
      }
    ],
    "imageUrl": "https://www.molottery.com/media/scratchers/tile/405.png"
  },
  {
    "name": "Top line",
    "price": 3.0,
    "totalTickets": 0,
    "remainingTickets": 0,
    "gameNumber": "409",
    "tiers": [
      {
        "prize": 50000,
        "remaining": 2,
        "total": 10
      },
      {
        "prize": 1000,
        "remaining": 8,
        "total": 114
      },
      {
        "prize": 500,
        "remaining": 67,
        "total": 746
      },
      {
        "prize": 100,
        "remaining": 858,
        "total": 11654
      },
      {
        "prize": 60,
        "remaining": 872,
        "total": 11364
      },
      {
        "prize": 50,
        "remaining": 1163,
        "total": 15112
      },
      {
        "prize": 20,
        "remaining": 7452,
        "total": 90672
      },
      {
        "prize": 16,
        "remaining": 3464,
        "total": 45362
      },
      {
        "prize": 10,
        "remaining": 17467,
        "total": 181396
      },
      {
        "prize": 9,
        "remaining": 18785,
        "total": 226602
      },
      {
        "prize": 6,
        "remaining": 86694,
        "total": 883981
      },
      {
        "prize": 3,
        "remaining": 114557,
        "total": 906784
      }
    ],
    "imageUrl": "https://www.molottery.com/media/scratchers/tile/409.png"
  },
  {
    "name": "Top line",
    "price": 20.0,
    "totalTickets": 0,
    "remainingTickets": 0,
    "gameNumber": "359",
    "tiers": [
      {
        "prize": 2000000,
        "remaining": 1,
        "total": 2
      },
      {
        "prize": 100000,
        "remaining": 1,
        "total": 4
      },
      {
        "prize": 20000,
        "remaining": 0,
        "total": 5
      },
      {
        "prize": 10000,
        "remaining": 2,
        "total": 11
      },
      {
        "prize": 5000,
        "remaining": 6,
        "total": 25
      },
      {
        "prize": 1000,
        "remaining": 205,
        "total": 1112
      },
      {
        "prize": 500,
        "remaining": 336,
        "total": 1801
      },
      {
        "prize": 200,
        "remaining": 1026,
        "total": 5451
      },
      {
        "prize": 100,
        "remaining": 24830,
        "total": 136387
      },
      {
        "prize": 50,
        "remaining": 25777,
        "total": 140485
      },
      {
        "prize": 40,
        "remaining": 61341,
        "total": 327303
      },
      {
        "prize": 20,
        "remaining": 89966,
        "total": 463709
      }
    ],
    "imageUrl": "https://www.molottery.com/media/scratchers/tile/359.png"
  }
]