[
  {
    "name": "$25,000 Grande",
    "price": 5.0,
    "totalTickets": 145575,
    "remainingTickets": 144721,
    "gameNumber": "690",
    "tiers": [
      {
        "prize": 25000,
        "remaining": 3,
        "total": 3
      },
      {
        "prize": 1000,
        "remaining": 10,
        "total": 10
      },
      {
        "prize": 200,
        "remaining": 28,
        "total": 28
      },
      {
        "prize": 100,
        "remaining": 128,
        "total": 130
      },
      {
        "prize": 50,
        "remaining": 1694,
        "total": 1702
      },
      {
        "prize": 40,
        "remaining": 4977,
        "total": 5006
      },
      {
        "prize": 20,
        "remaining": 4183,
        "total": 4209
      }
    ],
    "imageUrl": "https://www.nmlottery.com/wp-content/uploads/2026/07/690.jpg"
  },
  {
    "name": "$10,000 Grande Crossword",
    "price": 3.0,
    "totalTickets": 475370,
    "remainingTickets": 471190,
    "gameNumber": "689",
    "tiers": [
      {
        "prize": 10000,
        "remaining": 3,
        "total": 3
      },
      {
        "prize": 1000,
        "remaining": 10,
        "total": 10
      },
      {
        "prize": 100,
        "remaining": 250,
        "total": 252
      },
      {
        "prize": 50,
        "remaining": 994,
        "total": 1007
      },
      {
        "prize": 30,
        "remaining": 2045,
        "total": 2072
      },
      {
        "prize": 20,
        "remaining": 4919,
        "total": 4962
      },
      {
        "prize": 15,
        "remaining": 9823,
        "total": 9924
      },
      {
        "prize": 10,
        "remaining": 14734,
        "total": 14886
      },
      {
        "prize": 5,
        "remaining": 34414,
        "total": 34734
      },
      {
        "prize": 3,
        "remaining": 59082,
        "total": 59544
      }
    ],
    "imageUrl": "https://www.nmlottery.com/wp-content/uploads/2026/07/689.jpg"
  },
  {
    "name": "$5,000 Grande",
    "price": 2.0,
    "totalTickets": 446227,
    "remainingTickets": 444105,
    "gameNumber": "688",
    "tiers": [
      {
        "prize": 5000,
        "remaining": 3,
        "total": 3
      },
      {
        "prize": 100,
        "remaining": 195,
        "total": 196
      },
      {
        "prize": 50,
        "remaining": 492,
        "total": 492
      },
      {
        "prize": 40,
        "remaining": 1336,
        "total": 1350
      },
      {
        "prize": 20,
        "remaining": 3270,
        "total": 3288
      },
      {
        "prize": 10,
        "remaining": 9817,
        "total": 9872
      },
      {
        "prize": 5,
        "remaining": 19624,
        "total": 19728
      },
      {
        "prize": 3,
        "remaining": 26146,
        "total": 26272
      },
      {
        "prize": 2,
        "remaining": 22928,
        "total": 23036
      },
      {
        "prize": 2,
        "remaining": 39282,
        "total": 39444
      }
    ],
    "imageUrl": "https://www.nmlottery.com/wp-content/uploads/2026/07/688.jpg"
  },
  {
    "name": "$1,000 Grande",
    "price": 1.0,
    "totalTickets": 601936,
    "remainingTickets": 599635,
    "gameNumber": "687",
    "tiers": [
      {
        "prize": 1000,
        "remaining": 3,
        "total": 3
      },
      {
        "prize": 50,
        "remaining": 225,
        "total": 226
      },
      {
        "prize": 40,
        "remaining": 457,
        "total": 462
      },
      {
        "prize": 30,
        "remaining": 1346,
        "total": 1353
      },
      {
        "prize": 20,
        "remaining": 2210,
        "total": 2223
      },
      {
        "prize": 10,
        "remaining": 6632,
        "total": 6669
      },
      {
        "prize": 5,
        "remaining": 11061,
        "total": 11115
      },
      {
        "prize": 2,
        "remaining": 35435,
        "total": 35568
      },
      {
        "prize": 1,
        "remaining": 42081,
        "total": 42237
      },
      {
        "prize": 1,
        "remaining": 37671,
        "total": 37791
      }
    ],
    "imageUrl": "https://www.nmlottery.com/wp-content/uploads/2026/07/687.jpg"
  },
  {
    "name": "Gold Rush",
    "price": 10.0,
    "totalTickets": 336153,
    "remainingTickets": 303082,
    "gameNumber": "680",
    "tiers": [
      {
        "prize": 10000,
        "remaining": 2,
        "total": 3
      },
      {
        "prize": 1000,
        "remaining": 23,
        "total": 25
      },
      {
        "prize": 500,
        "remaining": 138,
        "total": 154
      },
      {
        "prize": 100,
        "remaining": 2177,
        "total": 2434
      },
      {
        "prize": 50,
        "remaining": 10834,
        "total": 12064
      },
      {
        "prize": 20,
        "remaining": 10908,
        "total": 12119
      },
      {
        "prize": 15,
        "remaining": 32550,
        "total": 36136
      },
      {
        "prize": 10,
        "remaining": 38158,
        "total": 42198
      }
    ],
    "imageUrl": "https://www.nmlottery.com/wp-content/uploads/2026/06/680.jpg"
  },
  {
    "name": "LOTERIA\u2122 Super Grande!",
    "price": 5.0,
    "totalTickets": 981895,
    "remainingTickets": 902098,
    "gameNumber": "645",
    "tiers": [
      {
        "prize": 50000,
        "remaining": 3,
        "total": 3
      },
      {
        "prize": 10000,
        "remaining": 2,
        "total": 3
      },
      {
        "prize": 5000,
        "remaining": 5,
        "total": 5
      },
      {
        "prize": 1000,
        "remaining": 9,
        "total": 10
      },
      {
        "prize": 500,
        "remaining": 91,
        "total": 100
      },
      {
        "prize": 200,
        "remaining": 372,
        "total": 411
      },
      {
        "prize": 100,
        "remaining": 910,
        "total": 997
      },
      {
        "prize": 50,
        "remaining": 2146,
        "total": 2349
      },
      {
        "prize": 40,
        "remaining": 3040,
        "total": 3359
      },
      {
        "prize": 30,
        "remaining": 4583,
        "total": 5027
      },
      {
        "prize": 20,
        "remaining": 15309,
        "total": 16725
      },
      {
        "prize": 15,
        "remaining": 45900,
        "total": 50165
      },
      {
        "prize": 10,
        "remaining": 61466,
        "total": 66919
      },
      {
        "prize": 5,
        "remaining": 107945,
        "total": 117095
      }
    ],
    "imageUrl": "https://www.nmlottery.com/wp-content/uploads/2026/06/645-1.jpg"
  },
  {
    "name": "Red Hot Double Doubler",
    "price": 1.0,
    "totalTickets": 610267,
    "remainingTickets": 541121,
    "gameNumber": "674",
    "tiers": [
      {
        "prize": 1000,
        "remaining": 6,
        "total": 6
      },
      {
        "prize": 500,
        "remaining": 7,
        "total": 8
      },
      {
        "prize": 250,
        "remaining": 16,
        "total": 18
      },
      {
        "prize": 100,
        "remaining": 81,
        "total": 89
      },
      {
        "prize": 50,
        "remaining": 408,
        "total": 454
      },
      {
        "prize": 40,
        "remaining": 595,
        "total": 692
      },
      {
        "prize": 20,
        "remaining": 1972,
        "total": 2258
      },
      {
        "prize": 10,
        "remaining": 3938,
        "total": 4516
      },
      {
        "prize": 8,
        "remaining": 3970,
        "total": 4516
      },
      {
        "prize": 4,
        "remaining": 15916,
        "total": 18064
      },
      {
        "prize": 2,
        "remaining": 15988,
        "total": 18064
      },
      {
        "prize": 1,
        "remaining": 54301,
        "total": 60966
      },
      {
        "prize": 1,
        "remaining": 24055,
        "total": 27096
      }
    ],
    "imageUrl": "https://www.nmlottery.com/wp-content/uploads/2026/06/674.jpg"
  },
  {
    "name": "100X",
    "price": 20.0,
    "totalTickets": 418546,
    "remainingTickets": 237515,
    "gameNumber": "628",
    "tiers": [
      {
        "prize": 100000,
        "remaining": 2,
        "total": 3
      },
      {
        "prize": 10000,
        "remaining": 2,
        "total": 5
      },
      {
        "prize": 2000,
        "remaining": 5,
        "total": 10
      },
      {
        "prize": 1000,
        "remaining": 7,
        "total": 10
      },
      {
        "prize": 500,
        "remaining": 63,
        "total": 115
      },
      {
        "prize": 100,
        "remaining": 6729,
        "total": 12509
      },
      {
        "prize": 50,
        "remaining": 14032,
        "total": 25018
      },
      {
        "prize": 40,
        "remaining": 20782,
        "total": 37520
      },
      {
        "prize": 20,
        "remaining": 29449,
        "total": 50050
      }
    ],
    "imageUrl": "https://www.nmlottery.com/wp-content/uploads/2025/03/628-1.jpg"
  },
  {
    "name": "Crossword Tripler",
    "price": 3.0,
    "totalTickets": 1585931,
    "remainingTickets": 1337207,
    "gameNumber": "682",
    "tiers": [
      {
        "prize": 30000,
        "remaining": 3,
        "total": 3
      },
      {
        "prize": 3000,
        "remaining": 7,
        "total": 8
      },
      {
        "prize": 100,
        "remaining": 741,
        "total": 899
      },
      {
        "prize": 50,
        "remaining": 1853,
        "total": 2239
      },
      {
        "prize": 30,
        "remaining": 6945,
        "total": 8415
      },
      {
        "prize": 20,
        "remaining": 13790,
        "total": 16635
      },
      {
        "prize": 15,
        "remaining": 27718,
        "total": 33516
      },
      {
        "prize": 10,
        "remaining": 41594,
        "total": 50150
      },
      {
        "prize": 5,
        "remaining": 97845,
        "total": 117019
      },
      {
        "prize": 3,
        "remaining": 171753,
        "total": 200744
      }
    ],
    "imageUrl": "https://www.nmlottery.com/wp-content/uploads/2026/05/682.jpg"
  },
  {
    "name": "I Love Cash",
    "price": 2.0,
    "totalTickets": 438998,
    "remainingTickets": 334915,
    "gameNumber": "686",
    "tiers": [
      {
        "prize": 5000,
        "remaining": 2,
        "total": 3
      },
      {
        "prize": 100,
        "remaining": 128,
        "total": 169
      },
      {
        "prize": 50,
        "remaining": 483,
        "total": 655
      },
      {
        "prize": 40,
        "remaining": 739,
        "total": 993
      },
      {
        "prize": 20,
        "remaining": 2413,
        "total": 3284
      },
      {
        "prize": 10,
        "remaining": 7327,
        "total": 9848
      },
      {
        "prize": 5,
        "remaining": 14888,
        "total": 19704
      },
      {
        "prize": 3,
        "remaining": 20113,
        "total": 26288
      },
      {
        "prize": 2,
        "remaining": 17756,
        "total": 22960
      },
      {
        "prize": 2,
        "remaining": 30245,
        "total": 39432
      }
    ],
    "imageUrl": "https://www.nmlottery.com/wp-content/uploads/2026/05/686.jpg"
  },
  {
    "name": "Xtra Bonus",
    "price": 1.0,
    "totalTickets": 537935,
    "remainingTickets": 430012,
    "gameNumber": "650",
    "tiers": [
      {
        "prize": 1000,
        "remaining": 2,
        "total": 3
      },
      {
        "prize": 100,
        "remaining": 189,
        "total": 240
      },
      {
        "prize": 50,
        "remaining": 553,
        "total": 716
      },
      {
        "prize": 20,
        "remaining": 1553,
        "total": 2006
      },
      {
        "prize": 10,
        "remaining": 4664,
        "total": 6018
      },
      {
        "prize": 5,
        "remaining": 7864,
        "total": 10030
      },
      {
        "prize": 2,
        "remaining": 25593,
        "total": 32096
      },
      {
        "prize": 1,
        "remaining": 27505,
        "total": 34102
      },
      {
        "prize": 1,
        "remaining": 30660,
        "total": 38114
      }
    ],
    "imageUrl": "https://www.nmlottery.com/wp-content/uploads/2026/05/650.jpg"
  },
  {
    "name": "Bingo Extra",
    "price": 3.0,
    "totalTickets": 922985,
    "remainingTickets": 742632,
    "gameNumber": "683",
    "tiers": [
      {
        "prize": 5000,
        "remaining": 3,
        "total": 3
      },
      {
        "prize": 500,
        "remaining": 18,
        "total": 21
      },
      {
        "prize": 100,
        "remaining": 1051,
        "total": 1329
      },
      {
        "prize": 50,
        "remaining": 2604,
        "total": 3335
      },
      {
        "prize": 20,
        "remaining": 7802,
        "total": 9964
      },
      {
        "prize": 15,
        "remaining": 7867,
        "total": 9967
      },
      {
        "prize": 10,
        "remaining": 31612,
        "total": 39853
      },
      {
        "prize": 5,
        "remaining": 64201,
        "total": 79709
      },
      {
        "prize": 3,
        "remaining": 48563,
        "total": 59768
      },
      {
        "prize": 3,
        "remaining": 40474,
        "total": 49836
      }
    ],
    "imageUrl": "https://www.nmlottery.com/wp-content/uploads/2026/04/683-1.jpg"
  },
  {
    "name": "Fast Cash",
    "price": 2.0,
    "totalTickets": 448289,
    "remainingTickets": 325965,
    "gameNumber": "655",
    "tiers": [
      {
        "prize": 500,
        "remaining": 14,
        "total": 20
      },
      {
        "prize": 100,
        "remaining": 140,
        "total": 198
      },
      {
        "prize": 50,
        "remaining": 1181,
        "total": 1679
      },
      {
        "prize": 20,
        "remaining": 2325,
        "total": 3303
      },
      {
        "prize": 10,
        "remaining": 7052,
        "total": 9909
      },
      {
        "prize": 5,
        "remaining": 14238,
        "total": 19818
      },
      {
        "prize": 3,
        "remaining": 19267,
        "total": 26424
      },
      {
        "prize": 2,
        "remaining": 29047,
        "total": 39636
      },
      {
        "prize": 2,
        "remaining": 16979,
        "total": 23121
      }
    ],
    "imageUrl": "https://www.nmlottery.com/wp-content/uploads/2026/04/655.jpg"
  },
  {
    "name": "Aces High",
    "price": 1.0,
    "totalTickets": 597030,
    "remainingTickets": 416367,
    "gameNumber": "649",
    "tiers": [
      {
        "prize": 500,
        "remaining": 11,
        "total": 16
      },
      {
        "prize": 100,
        "remaining": 118,
        "total": 183
      },
      {
        "prize": 30,
        "remaining": 789,
        "total": 1163
      },
      {
        "prize": 20,
        "remaining": 1486,
        "total": 2262
      },
      {
        "prize": 10,
        "remaining": 4518,
        "total": 6826
      },
      {
        "prize": 5,
        "remaining": 10701,
        "total": 15890
      },
      {
        "prize": 2,
        "remaining": 15758,
        "total": 22700
      },
      {
        "prize": 1,
        "remaining": 32166,
        "total": 45418
      },
      {
        "prize": 1,
        "remaining": 30394,
        "total": 43112
      }
    ],
    "imageUrl": "https://www.nmlottery.com/wp-content/uploads/2026/04/649-1.jpg"
  },
  {
    "name": "Cash Bonanza",
    "price": 20.0,
    "totalTickets": 344005,
    "remainingTickets": 263577,
    "gameNumber": "643",
    "tiers": [
      {
        "prize": 20000,
        "remaining": 2,
        "total": 3
      },
      {
        "prize": 1000,
        "remaining": 7,
        "total": 8
      },
      {
        "prize": 500,
        "remaining": 47,
        "total": 60
      },
      {
        "prize": 200,
        "remaining": 1389,
        "total": 1813
      },
      {
        "prize": 100,
        "remaining": 9265,
        "total": 12156
      },
      {
        "prize": 50,
        "remaining": 27888,
        "total": 36473
      },
      {
        "prize": 20,
        "remaining": 37351,
        "total": 48611
      }
    ],
    "imageUrl": "https://www.nmlottery.com/wp-content/uploads/2026/04/643.jpg"
  },
  {
    "name": "Triple Red 777s",
    "price": 10.0,
    "totalTickets": 348253,
    "remainingTickets": 238039,
    "gameNumber": "679",
    "tiers": [
      {
        "prize": 20000,
        "remaining": 2,
        "total": 3
      },
      {
        "prize": 5000,
        "remaining": 3,
        "total": 6
      },
      {
        "prize": 500,
        "remaining": 55,
        "total": 81
      },
      {
        "prize": 100,
        "remaining": 1652,
        "total": 2502
      },
      {
        "prize": 50,
        "remaining": 8214,
        "total": 12553
      },
      {
        "prize": 20,
        "remaining": 8497,
        "total": 12577
      },
      {
        "prize": 15,
        "remaining": 25822,
        "total": 37638
      },
      {
        "prize": 10,
        "remaining": 30450,
        "total": 43919
      }
    ],
    "imageUrl": "https://www.nmlottery.com/wp-content/uploads/2026/04/679.jpg"
  },
  {
    "name": "Legends of Lucha Libre\u00ae",
    "price": 5.0,
    "totalTickets": 509935,
    "remainingTickets": 292815,
    "gameNumber": "663",
    "tiers": [
      {
        "prize": 25000,
        "remaining": 2,
        "total": 3
      },
      {
        "prize": 5000,
        "remaining": 1,
        "total": 3
      },
      {
        "prize": 1000,
        "remaining": 2,
        "total": 3
      },
      {
        "prize": 500,
        "remaining": 19,
        "total": 40
      },
      {
        "prize": 100,
        "remaining": 314,
        "total": 596
      },
      {
        "prize": 50,
        "remaining": 928,
        "total": 1678
      },
      {
        "prize": 40,
        "remaining": 2741,
        "total": 4983
      },
      {
        "prize": 20,
        "remaining": 4649,
        "total": 8315
      },
      {
        "prize": 15,
        "remaining": 9293,
        "total": 16617
      },
      {
        "prize": 10,
        "remaining": 28467,
        "total": 49574
      },
      {
        "prize": 5,
        "remaining": 33887,
        "total": 58035
      }
    ],
    "imageUrl": "https://www.nmlottery.com/wp-content/uploads/2026/04/663-1.jpg"
  },
  {
    "name": "777",
    "price": 2.0,
    "totalTickets": 433720,
    "remainingTickets": 235905,
    "gameNumber": "654",
    "tiers": [
      {
        "prize": 7000,
        "remaining": 3,
        "total": 3
      },
      {
        "prize": 100,
        "remaining": 115,
        "total": 246
      },
      {
        "prize": 40,
        "remaining": 780,
        "total": 1603
      },
      {
        "prize": 20,
        "remaining": 1639,
        "total": 3198
      },
      {
        "prize": 10,
        "remaining": 5124,
        "total": 9608
      },
      {
        "prize": 5,
        "remaining": 10093,
        "total": 19188
      },
      {
        "prize": 3,
        "remaining": 13856,
        "total": 25528
      },
      {
        "prize": 2,
        "remaining": 21257,
        "total": 38384
      },
      {
        "prize": 2,
        "remaining": 12484,
        "total": 22392
      }
    ],
    "imageUrl": "https://www.nmlottery.com/wp-content/uploads/2026/04/654.jpg"
  },
  {
    "name": "Dinero Loco",
    "price": 1.0,
    "totalTickets": 608276,
    "remainingTickets": 393943,
    "gameNumber": "673",
    "tiers": [
      {
        "prize": 1000,
        "remaining": 2,
        "total": 3
      },
      {
        "prize": 100,
        "remaining": 157,
        "total": 277
      },
      {
        "prize": 40,
        "remaining": 715,
        "total": 1186
      },
      {
        "prize": 20,
        "remaining": 1347,
        "total": 2266
      },
      {
        "prize": 10,
        "remaining": 2822,
        "total": 4532
      },
      {
        "prize": 5,
        "remaining": 8335,
        "total": 13596
      },
      {
        "prize": 2,
        "remaining": 27033,
        "total": 40788
      },
      {
        "prize": 1,
        "remaining": 25007,
        "total": 38522
      },
      {
        "prize": 1,
        "remaining": 25052,
        "total": 38522
      }
    ],
    "imageUrl": "https://www.nmlottery.com/wp-content/uploads/2026/04/673.jpg"
  },
  {
    "name": "Crossword Deluxe",
    "price": 5.0,
    "totalTickets": 564849,
    "remainingTickets": 262815,
    "gameNumber": "676",
    "tiers": [
      {
        "prize": 5000,
        "remaining": 1,
        "total": 4
      },
      {
        "prize": 500,
        "remaining": 28,
        "total": 62
      },
      {
        "prize": 100,
        "remaining": 232,
        "total": 596
      },
      {
        "prize": 40,
        "remaining": 4184,
        "total": 10148
      },
      {
        "prize": 20,
        "remaining": 4304,
        "total": 10112
      },
      {
        "prize": 15,
        "remaining": 8571,
        "total": 20293
      },
      {
        "prize": 10,
        "remaining": 20250,
        "total": 45721
      },
      {
        "prize": 5,
        "remaining": 15326,
        "total": 30460
      },
      {
        "prize": 5,
        "remaining": 20626,
        "total": 40619
      }
    ],
    "imageUrl": "https://www.nmlottery.com/wp-content/uploads/2026/02/676.jpg"
  },
  {
    "name": "Lots of Cash",
    "price": 5.0,
    "totalTickets": 445892,
    "remainingTickets": 211946,
    "gameNumber": "666",
    "tiers": [
      {
        "prize": 10000,
        "remaining": 2,
        "total": 3
      },
      {
        "prize": 1000,
        "remaining": 3,
        "total": 6
      },
      {
        "prize": 200,
        "remaining": 19,
        "total": 40
      },
      {
        "prize": 100,
        "remaining": 152,
        "total": 340
      },
      {
        "prize": 40,
        "remaining": 3656,
        "total": 8310
      },
      {
        "prize": 20,
        "remaining": 7526,
        "total": 16620
      },
      {
        "prize": 10,
        "remaining": 17297,
        "total": 37397
      },
      {
        "prize": 5,
        "remaining": 32754,
        "total": 66476
      }
    ],
    "imageUrl": "https://www.nmlottery.com/wp-content/uploads/2026/02/666.jpg"
  },
  {
    "name": "7-11-21\u00ae Tripler",
    "price": 2.0,
    "totalTickets": 452507,
    "remainingTickets": 187449,
    "gameNumber": "671",
    "tiers": [
      {
        "prize": 2100,
        "remaining": 2,
        "total": 3
      },
      {
        "prize": 100,
        "remaining": 149,
        "total": 425
      },
      {
        "prize": 30,
        "remaining": 1240,
        "total": 3342
      },
      {
        "prize": 20,
        "remaining": 1173,
        "total": 3322
      },
      {
        "prize": 10,
        "remaining": 2491,
        "total": 6648
      },
      {
        "prize": 5,
        "remaining": 6599,
        "total": 16631
      },
      {
        "prize": 3,
        "remaining": 15249,
        "total": 36633
      },
      {
        "prize": 2,
        "remaining": 11347,
        "total": 26643
      },
      {
        "prize": 2,
        "remaining": 12958,
        "total": 29970
      }
    ],
    "imageUrl": "https://www.nmlottery.com/wp-content/uploads/2026/02/671.jpg"
  },
  {
    "name": "Great 8s",
    "price": 1.0,
    "totalTickets": 547610,
    "remainingTickets": 162686,
    "gameNumber": "651",
    "tiers": [
      {
        "prize": 500,
        "remaining": 2,
        "total": 7
      },
      {
        "prize": 100,
        "remaining": 39,
        "total": 170
      },
      {
        "prize": 50,
        "remaining": 133,
        "total": 527
      },
      {
        "prize": 20,
        "remaining": 498,
        "total": 2035
      },
      {
        "prize": 15,
        "remaining": 473,
        "total": 2034
      },
      {
        "prize": 10,
        "remaining": 549,
        "total": 2084
      },
      {
        "prize": 5,
        "remaining": 2083,
        "total": 8201
      },
      {
        "prize": 3,
        "remaining": 5655,
        "total": 20470
      },
      {
        "prize": 2,
        "remaining": 5997,
        "total": 20470
      },
      {
        "prize": 1,
        "remaining": 11711,
        "total": 36891
      },
      {
        "prize": 1,
        "remaining": 11389,
        "total": 36801
      }
    ],
    "imageUrl": "https://www.nmlottery.com/wp-content/uploads/2026/02/651.jpg"
  },
  {
    "name": "Fiery 5s",
    "price": 5.0,
    "totalTickets": 433875,
    "remainingTickets": 121718,
    "gameNumber": "677",
    "tiers": [
      {
        "prize": 5000,
        "remaining": 2,
        "total": 3
      },
      {
        "prize": 500,
        "remaining": 10,
        "total": 40
      },
      {
        "prize": 100,
        "remaining": 107,
        "total": 403
      },
      {
        "prize": 50,
        "remaining": 1231,
        "total": 4888
      },
      {
        "prize": 25,
        "remaining": 2073,
        "total": 8077
      },
      {
        "prize": 15,
        "remaining": 4316,
        "total": 16154
      },
      {
        "prize": 10,
        "remaining": 8814,
        "total": 32290
      },
      {
        "prize": 5,
        "remaining": 18937,
        "total": 64652
      }
    ],
    "imageUrl": "https://www.nmlottery.com/wp-content/uploads/2026/01/677.jpg"
  },
  {
    "name": "Betty Boop\u2122",
    "price": 2.0,
    "totalTickets": 927261,
    "remainingTickets": 652073,
    "gameNumber": "670",
    "tiers": [
      {
        "prize": 5000,
        "remaining": 3,
        "total": 4
      },
      {
        "prize": 100,
        "remaining": 344,
        "total": 512
      },
      {
        "prize": 40,
        "remaining": 4468,
        "total": 6672
      },
      {
        "prize": 20,
        "remaining": 4521,
        "total": 6672
      },
      {
        "prize": 10,
        "remaining": 9088,
        "total": 13344
      },
      {
        "prize": 5,
        "remaining": 18546,
        "total": 26688
      },
      {
        "prize": 3,
        "remaining": 56485,
        "total": 80064
      },
      {
        "prize": 2,
        "remaining": 37911,
        "total": 53376
      },
      {
        "prize": 2,
        "remaining": 42598,
        "total": 60048
      }
    ],
    "imageUrl": "https://www.nmlottery.com/wp-content/uploads/2026/01/670-2.jpg"
  },
  {
    "name": "MYSTERY CROSSWORD",
    "price": 10.0,
    "totalTickets": 347427,
    "remainingTickets": 190302,
    "gameNumber": "675",
    "tiers": [
      {
        "prize": 500,
        "remaining": 54,
        "total": 100
      },
      {
        "prize": 100,
        "remaining": 386,
        "total": 756
      },
      {
        "prize": 50,
        "remaining": 1414,
        "total": 2778
      },
      {
        "prize": 40,
        "remaining": 3254,
        "total": 6273
      },
      {
        "prize": 30,
        "remaining": 3205,
        "total": 6244
      },
      {
        "prize": 20,
        "remaining": 13152,
        "total": 24932
      },
      {
        "prize": 15,
        "remaining": 19823,
        "total": 37308
      },
      {
        "prize": 10,
        "remaining": 7114,
        "total": 12402
      },
      {
        "prize": 10,
        "remaining": 21775,
        "total": 37326
      }
    ],
    "imageUrl": "https://www.nmlottery.com/wp-content/uploads/2025/11/675-1.jpg"
  },
  {
    "name": "M\u00e1s Dinero",
    "price": 10.0,
    "totalTickets": 330658,
    "remainingTickets": 112294,
    "gameNumber": "672",
    "tiers": [
      {
        "prize": 5000,
        "remaining": 2,
        "total": 3
      },
      {
        "prize": 500,
        "remaining": 30,
        "total": 100
      },
      {
        "prize": 100,
        "remaining": 321,
        "total": 1062
      },
      {
        "prize": 50,
        "remaining": 3793,
        "total": 12363
      },
      {
        "prize": 20,
        "remaining": 7927,
        "total": 24755
      },
      {
        "prize": 15,
        "remaining": 8674,
        "total": 24726
      },
      {
        "prize": 10,
        "remaining": 17426,
        "total": 49394
      }
    ],
    "imageUrl": "https://www.nmlottery.com/wp-content/uploads/2025/11/672-1.jpg"
  },
  {
    "name": "Tic Tac Multiplier",
    "price": 1.0,
    "totalTickets": 560123,
    "remainingTickets": 118075,
    "gameNumber": "647",
    "tiers": [
      {
        "prize": 1000,
        "remaining": 1,
        "total": 3
      },
      {
        "prize": 200,
        "remaining": 3,
        "total": 25
      },
      {
        "prize": 100,
        "remaining": 19,
        "total": 172
      },
      {
        "prize": 50,
        "remaining": 85,
        "total": 647
      },
      {
        "prize": 20,
        "remaining": 401,
        "total": 3164
      },
      {
        "prize": 10,
        "remaining": 594,
        "total": 4242
      },
      {
        "prize": 5,
        "remaining": 1797,
        "total": 10570
      },
      {
        "prize": 2,
        "remaining": 7770,
        "total": 38052
      },
      {
        "prize": 1,
        "remaining": 8290,
        "total": 35938
      },
      {
        "prize": 1,
        "remaining": 8181,
        "total": 35938
      }
    ],
    "imageUrl": "https://www.nmlottery.com/wp-content/uploads/2025/11/647.jpg"
  },
  {
    "name": "Lucky Numbers",
    "price": 3.0,
    "totalTickets": 440982,
    "remainingTickets": 66812,
    "gameNumber": "646",
    "tiers": [
      {
        "prize": 500,
        "remaining": 2,
        "total": 20
      },
      {
        "prize": 100,
        "remaining": 20,
        "total": 167
      },
      {
        "prize": 50,
        "remaining": 87,
        "total": 847
      },
      {
        "prize": 30,
        "remaining": 505,
        "total": 4974
      },
      {
        "prize": 20,
        "remaining": 555,
        "total": 4966
      },
      {
        "prize": 15,
        "remaining": 597,
        "total": 4989
      },
      {
        "prize": 10,
        "remaining": 1891,
        "total": 14908
      },
      {
        "prize": 4,
        "remaining": 5475,
        "total": 34848
      },
      {
        "prize": 3,
        "remaining": 9866,
        "total": 59673
      }
    ],
    "imageUrl": "https://www.nmlottery.com/wp-content/uploads/2025/11/646.jpg"
  },
  {
    "name": "Hello Money",
    "price": 10.0,
    "totalTickets": 345738,
    "remainingTickets": 34546,
    "gameNumber": "581",
    "tiers": [
      {
        "prize": 20000,
        "remaining": 1,
        "total": 3
      },
      {
        "prize": 5000,
        "remaining": 1,
        "total": 7
      },
      {
        "prize": 1000,
        "remaining": 1,
        "total": 10
      },
      {
        "prize": 500,
        "remaining": 4,
        "total": 51
      },
      {
        "prize": 100,
        "remaining": 190,
        "total": 2493
      },
      {
        "prize": 50,
        "remaining": 959,
        "total": 12450
      },
      {
        "prize": 20,
        "remaining": 1079,
        "total": 12398
      },
      {
        "prize": 15,
        "remaining": 3816,
        "total": 37398
      },
      {
        "prize": 10,
        "remaining": 4782,
        "total": 43607
      }
    ],
    "imageUrl": "https://www.nmlottery.com/wp-content/uploads/2025/10/581.jpg"
  },
  {
    "name": "Merry Money 5X",
    "price": 2.0,
    "totalTickets": 446813,
    "remainingTickets": 141030,
    "gameNumber": "668",
    "tiers": [
      {
        "prize": 500,
        "remaining": 6,
        "total": 18
      },
      {
        "prize": 100,
        "remaining": 109,
        "total": 437
      },
      {
        "prize": 40,
        "remaining": 403,
        "total": 1660
      },
      {
        "prize": 20,
        "remaining": 1258,
        "total": 4986
      },
      {
        "prize": 10,
        "remaining": 1797,
        "total": 6662
      },
      {
        "prize": 5,
        "remaining": 3786,
        "total": 13270
      },
      {
        "prize": 3,
        "remaining": 9436,
        "total": 29868
      },
      {
        "prize": 2,
        "remaining": 15349,
        "total": 46472
      },
      {
        "prize": 2,
        "remaining": 7826,
        "total": 23260
      }
    ],
    "imageUrl": "https://www.nmlottery.com/wp-content/uploads/2025/10/668-2.jpg"
  },
  {
    "name": "Merry Money",
    "price": 1.0,
    "totalTickets": 584490,
    "remainingTickets": 184702,
    "gameNumber": "661",
    "tiers": [
      {
        "prize": 20,
        "remaining": 1098,
        "total": 4217
      },
      {
        "prize": 10,
        "remaining": 1615,
        "total": 6278
      },
      {
        "prize": 5,
        "remaining": 4828,
        "total": 18853
      },
      {
        "prize": 2,
        "remaining": 11093,
        "total": 31480
      },
      {
        "prize": 1,
        "remaining": 24470,
        "total": 75574
      }
    ],
    "imageUrl": "https://www.nmlottery.com/wp-content/uploads/2025/10/661-1.jpg"
  },
  {
    "name": "Neon 7",
    "price": 5.0,
    "totalTickets": 401741,
    "remainingTickets": 120187,
    "gameNumber": "665",
    "tiers": [
      {
        "prize": 700,
        "remaining": 5,
        "total": 20
      },
      {
        "prize": 250,
        "remaining": 8,
        "total": 30
      },
      {
        "prize": 70,
        "remaining": 148,
        "total": 575
      },
      {
        "prize": 35,
        "remaining": 1316,
        "total": 4822
      },
      {
        "prize": 20,
        "remaining": 4487,
        "total": 15928
      },
      {
        "prize": 10,
        "remaining": 14043,
        "total": 47784
      },
      {
        "prize": 5,
        "remaining": 17361,
        "total": 55748
      }
    ],
    "imageUrl": "https://www.nmlottery.com/wp-content/uploads/2025/09/665-1.jpg"
  },
  {
    "name": "Creepy Cash",
    "price": 2.0,
    "totalTickets": 228540,
    "remainingTickets": 32267,
    "gameNumber": "656",
    "tiers": [
      {
        "prize": 500,
        "remaining": 1,
        "total": 20
      },
      {
        "prize": 100,
        "remaining": 11,
        "total": 172
      },
      {
        "prize": 50,
        "remaining": 36,
        "total": 409
      },
      {
        "prize": 20,
        "remaining": 133,
        "total": 1652
      },
      {
        "prize": 10,
        "remaining": 561,
        "total": 4956
      },
      {
        "prize": 5,
        "remaining": 1302,
        "total": 11559
      },
      {
        "prize": 3,
        "remaining": 2423,
        "total": 16525
      },
      {
        "prize": 2,
        "remaining": 2870,
        "total": 18172
      },
      {
        "prize": 2,
        "remaining": 1845,
        "total": 11569
      }
    ],
    "imageUrl": "https://www.nmlottery.com/wp-content/uploads/2025/09/656.jpg"
  },
  {
    "name": "The Sky\u2019s the Limit",
    "price": 1.0,
    "totalTickets": 599929,
    "remainingTickets": 171710,
    "gameNumber": "662",
    "tiers": [
      {
        "prize": 1000,
        "remaining": 0,
        "total": 3
      },
      {
        "prize": 100,
        "remaining": 39,
        "total": 223
      },
      {
        "prize": 50,
        "remaining": 159,
        "total": 940
      },
      {
        "prize": 20,
        "remaining": 443,
        "total": 2237
      },
      {
        "prize": 10,
        "remaining": 1202,
        "total": 5582
      },
      {
        "prize": 5,
        "remaining": 3294,
        "total": 13443
      },
      {
        "prize": 2,
        "remaining": 10465,
        "total": 35789
      },
      {
        "prize": 1,
        "remaining": 11454,
        "total": 38020
      },
      {
        "prize": 1,
        "remaining": 12018,
        "total": 40281
      }
    ],
    "imageUrl": "https://www.nmlottery.com/wp-content/uploads/2025/09/662-1.jpg"
  },
  {
    "name": "The Return of the Pink Panther\u2122 Crossword",
    "price": 15.0,
    "totalTickets": 274285,
    "remainingTickets": 51578,
    "gameNumber": "601",
    "tiers": [
      {
        "prize": 15000,
        "remaining": 1,
        "total": 4
      },
      {
        "prize": 1000,
        "remaining": 2,
        "total": 8
      },
      {
        "prize": 500,
        "remaining": 1,
        "total": 31
      },
      {
        "prize": 200,
        "remaining": 38,
        "total": 250
      },
      {
        "prize": 100,
        "remaining": 110,
        "total": 608
      },
      {
        "prize": 50,
        "remaining": 1592,
        "total": 10241
      },
      {
        "prize": 30,
        "remaining": 5263,
        "total": 30266
      },
      {
        "prize": 20,
        "remaining": 5118,
        "total": 30292
      },
      {
        "prize": 15,
        "remaining": 3476,
        "total": 15131
      },
      {
        "prize": 15,
        "remaining": 3575,
        "total": 15143
      }
    ],
    "imageUrl": "https://www.nmlottery.com/wp-content/uploads/2025/08/601.jpg"
  },
  {
    "name": "10X the Cash",
    "price": 2.0,
    "totalTickets": 428846,
    "remainingTickets": 63012,
    "gameNumber": "652",
    "tiers": [
      {
        "prize": 2000,
        "remaining": 1,
        "total": 3
      },
      {
        "prize": 100,
        "remaining": 32,
        "total": 323
      },
      {
        "prize": 40,
        "remaining": 131,
        "total": 1640
      },
      {
        "prize": 20,
        "remaining": 345,
        "total": 3240
      },
      {
        "prize": 10,
        "remaining": 1044,
        "total": 9703
      },
      {
        "prize": 5,
        "remaining": 1547,
        "total": 12994
      },
      {
        "prize": 3,
        "remaining": 5815,
        "total": 38880
      },
      {
        "prize": 2,
        "remaining": 4189,
        "total": 25920
      },
      {
        "prize": 2,
        "remaining": 4802,
        "total": 29160
      }
    ],
    "imageUrl": "https://www.nmlottery.com/wp-content/uploads/2025/08/652.jpg"
  },
  {
    "name": "Triple Tripler",
    "price": 1.0,
    "totalTickets": 556490,
    "remainingTickets": 91846,
    "gameNumber": "648",
    "tiers": [
      {
        "prize": 900,
        "remaining": 1,
        "total": 10
      },
      {
        "prize": 90,
        "remaining": 12,
        "total": 127
      },
      {
        "prize": 60,
        "remaining": 26,
        "total": 253
      },
      {
        "prize": 27,
        "remaining": 225,
        "total": 2051
      },
      {
        "prize": 15,
        "remaining": 212,
        "total": 2051
      },
      {
        "prize": 9,
        "remaining": 758,
        "total": 6153
      },
      {
        "prize": 3,
        "remaining": 2707,
        "total": 18459
      },
      {
        "prize": 2,
        "remaining": 4150,
        "total": 26663
      },
      {
        "prize": 1,
        "remaining": 4089,
        "total": 22533
      },
      {
        "prize": 1,
        "remaining": 9549,
        "total": 53354
      }
    ],
    "imageUrl": "https://www.nmlottery.com/wp-content/uploads/2025/08/648.jpg"
  },
  {
    "name": "Wild Cash Multiplier",
    "price": 10.0,
    "totalTickets": 306498,
    "remainingTickets": 14411,
    "gameNumber": "642",
    "tiers": [
      {
        "prize": 5000,
        "remaining": 0,
        "total": 3
      },
      {
        "prize": 500,
        "remaining": 0,
        "total": 45
      },
      {
        "prize": 100,
        "remaining": 9,
        "total": 378
      },
      {
        "prize": 80,
        "remaining": 29,
        "total": 786
      },
      {
        "prize": 60,
        "remaining": 134,
        "total": 2509
      },
      {
        "prize": 40,
        "remaining": 623,
        "total": 12168
      },
      {
        "prize": 20,
        "remaining": 1254,
        "total": 24336
      },
      {
        "prize": 15,
        "remaining": 1028,
        "total": 24336
      },
      {
        "prize": 10,
        "remaining": 1675,
        "total": 36504
      }
    ],
    "imageUrl": "https://www.nmlottery.com/wp-content/uploads/2025/07/642.jpg"
  },
  {
    "name": "Bags of Money",
    "price": 3.0,
    "totalTickets": 435070,
    "remainingTickets": 53718,
    "gameNumber": "638",
    "tiers": [
      {
        "prize": 1000,
        "remaining": 1,
        "total": 3
      },
      {
        "prize": 500,
        "remaining": 1,
        "total": 16
      },
      {
        "prize": 100,
        "remaining": 5,
        "total": 81
      },
      {
        "prize": 50,
        "remaining": 39,
        "total": 431
      },
      {
        "prize": 30,
        "remaining": 435,
        "total": 5017
      },
      {
        "prize": 20,
        "remaining": 415,
        "total": 5018
      },
      {
        "prize": 15,
        "remaining": 433,
        "total": 5007
      },
      {
        "prize": 10,
        "remaining": 886,
        "total": 10019
      },
      {
        "prize": 5,
        "remaining": 4457,
        "total": 40192
      },
      {
        "prize": 3,
        "remaining": 8884,
        "total": 60204
      }
    ],
    "imageUrl": "https://www.nmlottery.com/wp-content/uploads/2025/07/638-1.jpg"
  },
  {
    "name": "Hit $200",
    "price": 5.0,
    "totalTickets": 331316,
    "remainingTickets": 20252,
    "gameNumber": "659",
    "tiers": [
      {
        "prize": 200,
        "remaining": 15,
        "total": 540
      },
      {
        "prize": 100,
        "remaining": 4,
        "total": 251
      },
      {
        "prize": 50,
        "remaining": 30,
        "total": 940
      },
      {
        "prize": 20,
        "remaining": 441,
        "total": 12368
      },
      {
        "prize": 15,
        "remaining": 517,
        "total": 12368
      },
      {
        "prize": 10,
        "remaining": 1354,
        "total": 24736
      },
      {
        "prize": 5,
        "remaining": 3415,
        "total": 43288
      }
    ],
    "imageUrl": "https://www.nmlottery.com/wp-content/uploads/2025/07/659.jpg"
  },
  {
    "name": "Hit $25",
    "price": 1.0,
    "totalTickets": 600867,
    "remainingTickets": 113724,
    "gameNumber": "657",
    "tiers": [
      {
        "prize": 25,
        "remaining": 428,
        "total": 4568
      },
      {
        "prize": 10,
        "remaining": 819,
        "total": 6843
      },
      {
        "prize": 5,
        "remaining": 1612,
        "total": 11436
      },
      {
        "prize": 2,
        "remaining": 6197,
        "total": 34264
      },
      {
        "prize": 1,
        "remaining": 8315,
        "total": 38830
      },
      {
        "prize": 1,
        "remaining": 9001,
        "total": 43396
      }
    ],
    "imageUrl": "https://www.nmlottery.com/wp-content/uploads/2025/07/657.jpg"
  },
  {
    "name": "Hit $50",
    "price": 2.0,
    "totalTickets": 454892,
    "remainingTickets": 68903,
    "gameNumber": "658",
    "tiers": [
      {
        "prize": 50,
        "remaining": 256,
        "total": 3360
      },
      {
        "prize": 20,
        "remaining": 299,
        "total": 3360
      },
      {
        "prize": 10,
        "remaining": 347,
        "total": 3360
      },
      {
        "prize": 5,
        "remaining": 3006,
        "total": 23520
      },
      {
        "prize": 3,
        "remaining": 4641,
        "total": 30240
      },
      {
        "prize": 2,
        "remaining": 4516,
        "total": 26880
      },
      {
        "prize": 2,
        "remaining": 5257,
        "total": 30240
      }
    ],
    "imageUrl": "https://www.nmlottery.com/wp-content/uploads/2025/07/658.jpg"
  },
  {
    "name": "Hit $500",
    "price": 10.0,
    "totalTickets": 340626,
    "remainingTickets": 15536,
    "gameNumber": "660",
    "tiers": [
      {
        "prize": 500,
        "remaining": 3,
        "total": 300
      },
      {
        "prize": 250,
        "remaining": 5,
        "total": 201
      },
      {
        "prize": 100,
        "remaining": 11,
        "total": 615
      },
      {
        "prize": 50,
        "remaining": 360,
        "total": 12202
      },
      {
        "prize": 20,
        "remaining": 853,
        "total": 24404
      },
      {
        "prize": 15,
        "remaining": 1210,
        "total": 24404
      },
      {
        "prize": 10,
        "remaining": 2618,
        "total": 48808
      }
    ],
    "imageUrl": "https://www.nmlottery.com/wp-content/uploads/2025/07/660.jpg"
  },
  {
    "name": "Money Bag Bingo",
    "price": 3.0,
    "totalTickets": 900538,
    "remainingTickets": 187477,
    "gameNumber": "631",
    "tiers": [
      {
        "prize": 10000,
        "remaining": 0,
        "total": 3
      },
      {
        "prize": 500,
        "remaining": 2,
        "total": 15
      },
      {
        "prize": 100,
        "remaining": 113,
        "total": 986
      },
      {
        "prize": 50,
        "remaining": 398,
        "total": 3227
      },
      {
        "prize": 20,
        "remaining": 1551,
        "total": 9724
      },
      {
        "prize": 15,
        "remaining": 1468,
        "total": 9726
      },
      {
        "prize": 10,
        "remaining": 5575,
        "total": 29143
      },
      {
        "prize": 6,
        "remaining": 7723,
        "total": 38988
      },
      {
        "prize": 5,
        "remaining": 10351,
        "total": 48591
      },
      {
        "prize": 3,
        "remaining": 13055,
        "total": 58335
      },
      {
        "prize": 3,
        "remaining": 13276,
        "total": 58304
      }
    ],
    "imageUrl": "https://www.nmlottery.com/wp-content/uploads/2025/07/631-1.jpg"
  },
  {
    "name": "JURASSIC PARK",
    "price": 10.0,
    "totalTickets": 396710,
    "remainingTickets": 16735,
    "gameNumber": "632",
    "tiers": [
      {
        "prize": 100000,
        "remaining": 1,
        "total": 3
      },
      {
        "prize": 10000,
        "remaining": 0,
        "total": 6
      },
      {
        "prize": 1000,
        "remaining": 0,
        "total": 10
      },
      {
        "prize": 500,
        "remaining": 0,
        "total": 27
      },
      {
        "prize": 100,
        "remaining": 49,
        "total": 3758
      },
      {
        "prize": 50,
        "remaining": 298,
        "total": 12547
      },
      {
        "prize": 20,
        "remaining": 617,
        "total": 18811
      },
      {
        "prize": 15,
        "remaining": 1172,
        "total": 25113
      },
      {
        "prize": 10,
        "remaining": 2258,
        "total": 43905
      }
    ],
    "imageUrl": "https://www.nmlottery.com/wp-content/uploads/2025/06/632-1.jpg"
  },
  {
    "name": "Daily Crossword",
    "price": 3.0,
    "totalTickets": 1567144,
    "remainingTickets": 162463,
    "gameNumber": "639",
    "tiers": [
      {
        "prize": 30000,
        "remaining": 0,
        "total": 3
      },
      {
        "prize": 3000,
        "remaining": 0,
        "total": 8
      },
      {
        "prize": 200,
        "remaining": 4,
        "total": 169
      },
      {
        "prize": 100,
        "remaining": 18,
        "total": 568
      },
      {
        "prize": 50,
        "remaining": 60,
        "total": 2241
      },
      {
        "prize": 30,
        "remaining": 259,
        "total": 6991
      },
      {
        "prize": 20,
        "remaining": 519,
        "total": 16752
      },
      {
        "prize": 15,
        "remaining": 1087,
        "total": 33504
      },
      {
        "prize": 10,
        "remaining": 2412,
        "total": 50256
      },
      {
        "prize": 5,
        "remaining": 8298,
        "total": 117264
      },
      {
        "prize": 3,
        "remaining": 31794,
        "total": 201024
      }
    ],
    "imageUrl": "https://www.nmlottery.com/wp-content/uploads/2025/05/639-1.jpg"
  },
  {
    "name": "Cherry Twist",
    "price": 2.0,
    "totalTickets": 453953,
    "remainingTickets": 76271,
    "gameNumber": "637",
    "tiers": [
      {
        "prize": 5000,
        "remaining": 0,
        "total": 3
      },
      {
        "prize": 100,
        "remaining": 53,
        "total": 337
      },
      {
        "prize": 50,
        "remaining": 255,
        "total": 1656
      },
      {
        "prize": 20,
        "remaining": 631,
        "total": 3276
      },
      {
        "prize": 10,
        "remaining": 1924,
        "total": 9828
      },
      {
        "prize": 5,
        "remaining": 2140,
        "total": 16380
      },
      {
        "prize": 3,
        "remaining": 4576,
        "total": 29484
      },
      {
        "prize": 2,
        "remaining": 6275,
        "total": 36004
      },
      {
        "prize": 2,
        "remaining": 4847,
        "total": 26240
      }
    ],
    "imageUrl": "https://www.nmlottery.com/wp-content/uploads/2025/05/637.jpg"
  },
  {
    "name": "Cool Cat",
    "price": 1.0,
    "totalTickets": 563089,
    "remainingTickets": 118335,
    "gameNumber": "634",
    "tiers": [
      {
        "prize": 500,
        "remaining": 1,
        "total": 7
      },
      {
        "prize": 100,
        "remaining": 21,
        "total": 210
      },
      {
        "prize": 50,
        "remaining": 70,
        "total": 615
      },
      {
        "prize": 20,
        "remaining": 230,
        "total": 2043
      },
      {
        "prize": 15,
        "remaining": 222,
        "total": 2074
      },
      {
        "prize": 10,
        "remaining": 247,
        "total": 2072
      },
      {
        "prize": 5,
        "remaining": 1235,
        "total": 8216
      },
      {
        "prize": 3,
        "remaining": 3728,
        "total": 20580
      },
      {
        "prize": 2,
        "remaining": 4254,
        "total": 20580
      },
      {
        "prize": 1,
        "remaining": 8820,
        "total": 37052
      },
      {
        "prize": 1,
        "remaining": 8594,
        "total": 37036
      }
    ],
    "imageUrl": "https://www.nmlottery.com/wp-content/uploads/2025/05/634.jpg"
  },
  {
    "name": "SKEE-BALL\u00ae",
    "price": 3.0,
    "totalTickets": 456772,
    "remainingTickets": 44169,
    "gameNumber": "633",
    "tiers": [
      {
        "prize": 15000,
        "remaining": 0,
        "total": 3
      },
      {
        "prize": 1000,
        "remaining": 0,
        "total": 5
      },
      {
        "prize": 500,
        "remaining": 1,
        "total": 10
      },
      {
        "prize": 200,
        "remaining": 0,
        "total": 33
      },
      {
        "prize": 100,
        "remaining": 4,
        "total": 82
      },
      {
        "prize": 50,
        "remaining": 10,
        "total": 169
      },
      {
        "prize": 30,
        "remaining": 263,
        "total": 4954
      },
      {
        "prize": 20,
        "remaining": 264,
        "total": 4950
      },
      {
        "prize": 15,
        "remaining": 275,
        "total": 4954
      },
      {
        "prize": 10,
        "remaining": 671,
        "total": 9893
      },
      {
        "prize": 5,
        "remaining": 3568,
        "total": 39678
      },
      {
        "prize": 3,
        "remaining": 7431,
        "total": 64402
      }
    ],
    "imageUrl": "https://www.nmlottery.com/wp-content/uploads/2025/04/633.jpg"
  },
  {
    "name": "Double Your Luck",
    "price": 10.0,
    "totalTickets": 383483,
    "remainingTickets": 239231,
    "gameNumber": "629",
    "tiers": [
      {
        "prize": 10000,
        "remaining": 2,
        "total": 3
      },
      {
        "prize": 1000,
        "remaining": 6,
        "total": 10
      },
      {
        "prize": 500,
        "remaining": 15,
        "total": 25
      },
      {
        "prize": 100,
        "remaining": 746,
        "total": 1215
      },
      {
        "prize": 80,
        "remaining": 2860,
        "total": 4607
      },
      {
        "prize": 40,
        "remaining": 15117,
        "total": 24376
      },
      {
        "prize": 20,
        "remaining": 15166,
        "total": 24372
      },
      {
        "prize": 10,
        "remaining": 30573,
        "total": 48760
      }
    ],
    "imageUrl": "https://www.nmlottery.com/wp-content/uploads/2025/02/629.jpg"
  },
  {
    "name": "Money Rush",
    "price": 5.0,
    "totalTickets": 1008486,
    "remainingTickets": 87465,
    "gameNumber": "618",
    "tiers": [
      {
        "prize": 50000,
        "remaining": 1,
        "total": 3
      },
      {
        "prize": 5000,
        "remaining": 0,
        "total": 4
      },
      {
        "prize": 1000,
        "remaining": 0,
        "total": 5
      },
      {
        "prize": 500,
        "remaining": 0,
        "total": 10
      },
      {
        "prize": 100,
        "remaining": 43,
        "total": 1382
      },
      {
        "prize": 50,
        "remaining": 545,
        "total": 16441
      },
      {
        "prize": 20,
        "remaining": 833,
        "total": 16475
      },
      {
        "prize": 15,
        "remaining": 1721,
        "total": 32863
      },
      {
        "prize": 10,
        "remaining": 4991,
        "total": 73939
      },
      {
        "prize": 5,
        "remaining": 14088,
        "total": 115099
      }
    ],
    "imageUrl": "https://www.nmlottery.com/wp-content/uploads/2025/02/618.jpg"
  },
  {
    "name": "Lucky 7s",
    "price": 3.0,
    "totalTickets": 719372,
    "remainingTickets": 69368,
    "gameNumber": "627",
    "tiers": [
      {
        "prize": 500,
        "remaining": 1,
        "total": 100
      },
      {
        "prize": 100,
        "remaining": 14,
        "total": 705
      },
      {
        "prize": 40,
        "remaining": 256,
        "total": 7412
      },
      {
        "prize": 20,
        "remaining": 289,
        "total": 7399
      },
      {
        "prize": 15,
        "remaining": 235,
        "total": 7412
      },
      {
        "prize": 10,
        "remaining": 1223,
        "total": 22262
      },
      {
        "prize": 4,
        "remaining": 6403,
        "total": 59296
      },
      {
        "prize": 3,
        "remaining": 10241,
        "total": 88944
      }
    ],
    "imageUrl": "https://www.nmlottery.com/wp-content/uploads/2024/12/627-1.jpg"
  },
  {
    "name": "Sizzling Riches",
    "price": 20.0,
    "totalTickets": 493016,
    "remainingTickets": 302222,
    "gameNumber": "608",
    "tiers": [
      {
        "prize": 200000,
        "remaining": 2,
        "total": 3
      },
      {
        "prize": 10000,
        "remaining": 3,
        "total": 4
      },
      {
        "prize": 5000,
        "remaining": 6,
        "total": 10
      },
      {
        "prize": 1000,
        "remaining": 18,
        "total": 30
      },
      {
        "prize": 500,
        "remaining": 261,
        "total": 416
      },
      {
        "prize": 100,
        "remaining": 8902,
        "total": 14618
      },
      {
        "prize": 50,
        "remaining": 13366,
        "total": 21873
      },
      {
        "prize": 40,
        "remaining": 26862,
        "total": 43854
      },
      {
        "prize": 20,
        "remaining": 36026,
        "total": 58580
      }
    ],
    "imageUrl": "https://www.nmlottery.com/wp-content/uploads/2024/12/608.jpg"
  },
  {
    "name": "$25, $50 or $100!",
    "price": 10.0,
    "totalTickets": 646984,
    "remainingTickets": 258642,
    "gameNumber": "624",
    "tiers": [
      {
        "prize": 100,
        "remaining": 8473,
        "total": 21590
      },
      {
        "prize": 50,
        "remaining": 8125,
        "total": 20430
      },
      {
        "prize": 25,
        "remaining": 16589,
        "total": 40996
      }
    ],
    "imageUrl": "https://www.nmlottery.com/wp-content/uploads/2024/11/624.jpg"
  },
  {
    "name": "Bonus Money",
    "price": 10.0,
    "totalTickets": 371620,
    "remainingTickets": 178492,
    "gameNumber": "598",
    "tiers": [
      {
        "prize": 10000,
        "remaining": 1,
        "total": 3
      },
      {
        "prize": 500,
        "remaining": 13,
        "total": 30
      },
      {
        "prize": 200,
        "remaining": 74,
        "total": 154
      },
      {
        "prize": 100,
        "remaining": 1853,
        "total": 3965
      },
      {
        "prize": 50,
        "remaining": 5912,
        "total": 12537
      },
      {
        "prize": 20,
        "remaining": 11945,
        "total": 25058
      },
      {
        "prize": 15,
        "remaining": 12043,
        "total": 25077
      },
      {
        "prize": 10,
        "remaining": 21344,
        "total": 43907
      }
    ],
    "imageUrl": "https://www.nmlottery.com/wp-content/uploads/2024/07/598.jpg"
  }
]